Workbook

Sheet 00_README
A1: MEM model-ready workbook v2.8 — six physical scenarios finalized | B1: MEM model-ready workbook v2.8 — six physical scenarios finalized | C1: MEM model-ready workbook v2.8 — six physical scenarios finalized | D1: MEM model-ready workbook v2.8 — six physical scenarios finalized | E1: MEM model-ready workbook v2.8 — six physical scenarios finalized | F1: MEM model-ready workbook v2.8 — six physical scenarios finalized | G1: MEM model-ready workbook v2.8 — six physical scenarios finalized | H1: MEM model-ready workbook v2.8 — six physical scenarios finalized | I1: MEM model-ready workbook v2.8 — six physical scenarios finalized | J1: MEM model-ready workbook v2.8 — six physical scenarios finalized
A2: Successor to v2.7. Fixed user-supplied 2025 zonal demand shares, formula-driven Slow/Base/High cases, project-level network delays, and evidence-bounded dispatchable controls. | B2: Successor to v2.7. Fixed user-supplied 2025 zonal demand shares, formula-driven Slow/Base/High cases, project-level network delays, and evidence-bounded dispatchable controls. | C2: Successor to v2.7. Fixed user-supplied 2025 zonal demand shares, formula-driven Slow/Base/High cases, project-level network delays, and evidence-bounded dispatchable controls. | D2: Successor to v2.7. Fixed user-supplied 2025 zonal demand shares, formula-driven Slow/Base/High cases, project-level network delays, and evidence-bounded dispatchable controls. | E2: Successor to v2.7. Fixed user-supplied 2025 zonal demand shares, formula-driven Slow/Base/High cases, project-level network delays, and evidence-bounded dispatchable controls. | F2: Successor to v2.7. Fixed user-supplied 2025 zonal demand shares, formula-driven Slow/Base/High cases, project-level network delays, and evidence-bounded dispatchable controls. | G2: Successor to v2.7. Fixed user-supplied 2025 zonal demand shares, formula-driven Slow/Base/High cases, project-level network delays, and evidence-bounded dispatchable controls. | H2: Successor to v2.7. Fixed user-supplied 2025 zonal demand shares, formula-driven Slow/Base/High cases, project-level network delays, and evidence-bounded dispatchable controls. | I2: Successor to v2.7. Fixed user-supplied 2025 zonal demand shares, formula-driven Slow/Base/High cases, project-level network delays, and evidence-bounded dispatchable controls. | J2: Successor to v2.7. Fixed user-supplied 2025 zonal demand shares, formula-driven Slow/Base/High cases, project-level network delays, and evidence-bounded dispatchable controls.
A4: Item | B4: v2.8 controlling rule | C4: Evidence / boundary
A5: Headline scenarios | B5: Exactly IT2040_SLOW, IT2040_BASE, IT2040_HIGH, IT2050_SLOW, IT2050_BASE, IT2050_HIGH | C5: GA-IT, PNIEC Slow, no-nuclear, CO2, nuclear-availability and weather cases remain secondary overlays.
A6: Base cases | B6: 2040 DE-IT; 2050 PNIEC with 8 GW nuclear | C6: v2.7 analytical baseline retained.
A7: Demand geography | B7: Fixed shares from MEM_2025_ZONAL_DEMAND_FROZEN.csv for total, rigid and P2X | C7: CNORD source label maps to CNOR model zone. No PyPSA-Eur/population reconstruction.
A8: Slow | B8: Base demand; FER and BESS power/energy x0.80; unchanged duration/efficiency; all network projects delayed two years | C8: 2050 Slow network equals recomputed 2040 Slow network.
A9: High | B9: Demand, FER and BESS power/energy x1.10; unchanged duration/efficiency; Base network exactly | C9: No accelerated/new Terna HV project. Distribution flexibility is implicit and outside the HV-zonal model boundary.
A10: Dispatchable 2040 | B10: 55 GW national thermoelectric envelope in all three headline cases | C10: No published CCGT/OCGT or zonal split; plant/cohort geography is a model allocation.
A11: Programmable 2050 | B11: >=30 GW approximate all-programmable adequacy floor in all three headline cases | C11: Not an exact gas total. PNIEC non-nuclear programmable generation is 22.7 TWh; installed technology MW are absent.
A12: Nuclear | B12: 8 GW (5 NORD, 3 CSUD) in every 2050 headline case | C12: Availability variants remain overlays; nuclear is not multiplied with FER.
A13: Network change in Slow | B13: Only 546-P, 563-P and 732-P fall outside 2040 after delay | C13: Every directional delta traces to MEM_v2.8_NETWORK_DELAY_REGISTER.csv.
A14: Reports | B14: No DOCX or PDF edited in this sprint | C14: Final narrative files remain baselines only.
A16: Read 02_SCENARIOS first. Derived scenario values are formulas; external CSV registers provide project/evidence audit trails. | B16: Read 02_SCENARIOS first. Derived scenario values are formulas; external CSV registers provide project/evidence audit trails. | C16: Read 02_SCENARIOS first. Derived scenario values are formulas; external CSV registers provide project/evidence audit trails. | D16: Read 02_SCENARIOS first. Derived scenario values are formulas; external CSV registers provide project/evidence audit trails. | E16: Read 02_SCENARIOS first. Derived scenario values are formulas; external CSV registers provide project/evidence audit trails. | F16: Read 02_SCENARIOS first. Derived scenario values are formulas; external CSV registers provide project/evidence audit trails. | G16: Read 02_SCENARIOS first. Derived scenario values are formulas; external CSV registers provide project/evidence audit trails. | H16: Read 02_SCENARIOS first. Derived scenario values are formulas; external CSV registers provide project/evidence audit trails. | I16: Read 02_SCENARIOS first. Derived scenario values are formulas; external CSV registers provide project/evidence audit trails. | J16: Read 02_SCENARIOS first. Derived scenario values are formulas; external CSV registers provide project/evidence audit trails.

Sheet 01_SOURCES
A1: Registro delle fonti
A2: Fonti ufficiali e benchmark utilizzati nella costruzione degli input. Gli URL sono mantenuti in chiaro.
A4: Source ID | B4: Documento | C4: Autore | D4: Anno | E4: Tipo | F4: Versione/data | G4: Ruolo principale | H4: Scenari | I4: Anni coperti | J4: Geografia | K4: Tecnologie | L4: Contenuto quantitativo | M4: Stato revisione | N4: Uso finale | O4: File / URL | P4: Note
A5: S01 | B5: Stato del sistema elettrico e scenari energetici | C5: Terna S.p.A. | D5: 2025 | E5: Piano di Sviluppo Terna - fascicolo tecnico | F5: Marzo 2025 (PDF modificato 13 marzo 2025) | G5: Baseline storica 2023-2024; struttura del mercato; scenari elettrici 2030-2040; bilanci, capacità e carico residuo. | H5: Storico 2023-2024; PNIEC Policy 2030; PNIEC Slow 2030/2035/2040; DE-IT 2035/2040; richiamo GA-IT/DDS24. | I5: Storico fino al 2024; scenari 2030, 2035, 2040. | J5: Nazionale; zone di mercato; alcune mappe regionali/territoriali; frontiere estere. | K5: Solare, eolico, idroelettrico, bioenergie/altre FER, gas, carbone/olio, accumuli elettrochimici, pompaggi, elettrolizzatori. | L5: Molto elevato: tabelle, mappe, grafici e bilanci. | M5: REVIEWED | N5: CORE | O5: Terna_Piano_Sviluppo_2025_Stato_sistema_elettrico_scenari_energetici_8dd62ec4bbb9f75.pdf | P5: PDF testuale; tabelle parzialmente estraibili; mappe e grafici richiedono verifica visuale/digitalizzazione.
A6: S02 | B6: Piano di Sviluppo 2025 - Overview | C6: Terna S.p.A. | D6: 2025 | E6: Piano di Sviluppo Terna - overview | F6: Marzo 2025 (PDF modificato 13 marzo 2025) | G6: Mappa sintetica del PdS 2025; cross-check di scenari, mercato, investimenti e cronologia rete 2030-2040. | H6: PNIEC/DDS24; orizzonti 2030, 2034 e 2040. | I6: Contesto storico recente; 2030, 2034, 2040. | J6: Nazionale, zonale e interconnessioni estere. | K6: FER, accumuli, generazione termica, data center; infrastrutture AC/HVDC. | L6: Medio-alto: indicatori sintetici, mappe e timeline. | M6: REVIEWED | N6: SUPPORTING | O6: Terna_Piano_Sviluppo_2025_Overview_8dd62ebfc87edf6.pdf | P6: PDF testuale; molti grafici sintetici e mappe da verificare visualmente.
A7: S03 | B7: Benefici di sistema e analisi robustezza rete | C7: Terna S.p.A. | D7: 2025 | E7: Piano di Sviluppo Terna - fascicolo tecnico | F7: Marzo 2025 (PDF modificato 13 marzo 2025) | G7: Capacità di trasporto, effetti con/senza interventi, congestioni, adeguatezza, FER, riserva, emissioni e perdite. | H7: PNIEC 2030; DE-IT 2035/2040; analisi con e senza sviluppi di rete. | I7: 2030, 2035, 2040; confronti con rete di riferimento. | J7: Frontiere estere; zone di mercato italiane; corridoi e aree di rete. | K7: FER, termoelettrico, accumuli; interventi AC/HVDC; risorse inverter-based. | L7: Elevato: capacità, benefici, indicatori di adeguatezza e mappe. | M7: REVIEWED | N7: CORE | O7: Terna_Piano_Sviluppo_2025_Benefici_sistema_analisi_robustezza_rete_8dd62ecc98b2bc9.pdf | P7: PDF testuale; tabelle discrete; mappe/capacità richiedono controllo visuale.
A8: S04 | B8: Programmazione territoriale efficiente e interventi di connessione | C8: Terna S.p.A. | D8: 2025 | E8: Piano di Sviluppo Terna - fascicolo tecnico | F8: Marzo 2025 (PDF modificato 13 marzo 2025) | G8: Pipeline territoriale di connessione; distribuzione regionale/locale; microzone; grandi carichi e opere di connessione. | H8: Richieste 2023-2024; confronto PNIEC Policy 2030; approccio microzonale prospettico. | I8: Storico richieste fino a dicembre 2024; target 2030; progetti in corso. | J8: Nazionale, regionale, provinciale/comunale e microzonale. | K8: Solare, eolico on/offshore, BESS, pompaggi, termoelettrico; data center, RFI, cold ironing, cabine primarie. | L8: Molto elevato: mappe regionali, tabelle pipeline e appendici progetto. | M8: REVIEWED | N8: SUPPORTING | O8: Terna_Piano_Sviluppo_2025_Programmazione_territoriale_efficiente_interventi_connessione_8dd62ec86ec25d1.pdf | P8: PDF testuale ma con numerose mappe/infografiche; appendici tabellari estraibili con revisione.
A9: S05 | B9: Esigenze di sviluppo: i nuovi progetti | C9: Terna S.p.A. | D9: 2025 | E9: Piano di Sviluppo Terna - fascicolo progetti | F9: Marzo 2025 (PDF modificato 13 marzo 2025) | G9: Architettura futura della RTN, capacità interzonali/estere, Hypergrid, cronologia e stato dei progetti. | H9: Target capacity e architetture 2030, 2034, 2040. | I9: 2025-2034; orizzonte architetturale 2040. | J9: Aree Nord-Ovest, Nord-Est, Centro-Sud; zone e frontiere estere; singoli corridoi/progetti. | K9: Linee AC, HVDC/VSC, reconductoring, DTR, stazioni e interconnector. | L9: Elevato: mappe, schede e tabelle di progetto. | M9: REVIEWED | N9: SUPPORTING | O9: Terna_Piano_Sviluppo_2025_Esigenze_sviluppo_nuovi_progetti_8dd62eca67348ba.pdf | P9: PDF testuale; schede progetto e mappe richiedono estrazione strutturata e controllo visuale.
A10: S06 | B10: Pianificazione della rete elettrica | C10: Terna S.p.A. | D10: 2025 | E10: Piano di Sviluppo Terna - fascicolo metodologico | F10: Marzo 2025 (PDF modificato 13 marzo 2025) | G10: Quadro metodologico, normativo e istituzionale; coordinamento TSO-DSO, TYNDP, storage e nuovi carichi. | H10: Pianificazione decennale; TYNDP e cooperazione europea/mediterranea. | I10: 2025-2034; programmi UE 2021-2027; riferimenti prospettici. | J10: Italia, Europa, Mediterraneo; casi nazionali. | K10: Storage, data center, cold ironing, e-mobility; digitalizzazione rete. | L10: Basso-medio: prevalenza descrittiva, alcune figure/tabelle. | M10: REVIEWED | N10: SUPPORTING | O10: Terna_Piano_Sviluppo_2025_Pianificazione_Rete_Elettrica_8dd62ec2378ac53.pdf | P10: PDF testuale; dati numerici limitati.
A11: S07 | B11: Prospettive di Sviluppo del Sistema Energetico 2050 - Copertura della domanda elettrica | C11: Terna S.p.A. | D11: 2025 | E11: Nota tecnica Terna ex Delibera ARERA 392/2024 | F11: 2025 (PDF creato/modificato 27 ottobre 2025) | G11: Fonte primaria 2050: domanda, mix, accumuli, costi tecnologici, adeguatezza e flessibilità. | H11: DDS24 2030-2040; scenari PNIEC 2050 con e senza nucleare; analisi di sensitività. | I11: Storico 2019-2025; 2030, 2040, 2050. | J11: Prevalentemente nazionale; profili temporali nazionali. | K11: Solare, eolico on/offshore, batterie, idroelettrico, gas, nucleare, CCUS/CCS, tecnologie emergenti. | L11: Molto elevato: costi, capacità, bilanci, domanda e flessibilità. | M11: REVIEWED | N11: CORE | O11: Terna Prospettive Sviluppo Sistema Energetico 2050.pdf | P11: PDF testuale; tabelle estraibili; numerosi grafici richiedono verifica/digitalizzazione.
A12: S08 | B12: Piano Nazionale Integrato per l'Energia e il Clima | C12: MASE | D12: 2024 | E12: Piano nazionale energia e clima | F12: Giugno 2024 | G12: Target ufficiali, traiettorie di policy, domanda/consumi settoriali, interconnessioni, prezzi e base analitica. | H12: Scenario di riferimento/WEM; scenario con politiche aggiuntive/PNIEC; proiezioni fino al 2040; ipotesi nucleare 2035-2050. | I12: Storico fino al 2022/2023; obiettivi 2030; proiezioni 2040; alcune ipotesi 2050. | J12: Prevalentemente nazionale; alcuni dati regionali/settoriali; interconnessioni transfrontaliere. | K12: FER elettriche/termiche/trasporti, termoelettrico, nucleare, idrogeno, CCS, reti e accumuli. | L12: Molto elevato ma disperso in 491 pagine. | M12: REVIEWED | N12: CORE | O12: PNIEC 2024.pdf | P12: PDF testuale; molte tabelle estraibili, alcune complesse; figure e note richiedono controllo.
A13: S09 | B13: Documento di Descrizione degli Scenari 2024 | C13: Terna e Snam | D13: 2024 | E13: Documento congiunto di scenario tecnico | F13: 2024 | G13: Fonte primaria 2030-2040 per domanda, capacità FER, bilanci, commodity e risultati di simulazione. | H13: PNIEC Policy; PNIEC Slow; DE-IT; GA-IT | I13: 2023; 2030; 2035; 2040 | J13: Nazionale e sette zone per solare, eolico, accumuli ed elettrolizzatori. | K13: Domanda; FER; storage; H2; termoelettrico aggregato; commodity; bilanci; flussi. | L13: Molto elevato: tabelle e figure direttamente utilizzabili. | M13: REVIEWED | N13: CORE | O13: Documento_Descrizione_Scenari_2024_8dce2430d44d101.pdf | P13: PDF testuale; tabelle estraibili e pagine quantitative verificate visivamente.
A14: S10 | B14: Allegato A.24 al Codice di Rete - Individuazione zone della rete rilevante | C14: Terna | D14: 2021 | E14: Codice di Rete / zonizzazione | F14: Rev. 05 - gennaio 2021 | G14: Definizione ufficiale delle zone NORD e CENTRO SUD | H14: Tutti | I14: Dal 2021 | J14: Italia | K14: Rete / zone di mercato | L14: Composizione regionale delle zone di mercato | M14: REVIEWED | N14: CORE | O14: https://download.terna.it/terna/Allegato%20A.24%20-%20Individuazione%20zone%20della%20rete%20rilevante_8d8bc86c78365d0.pdf | P14: Veneto e Piemonte appartengono alla zona NORD; Lazio alla zona CENTRO SUD.
A15: S11 | B15: Dichiarazione ambientale della Centrale nucleare di Trino | C15: Sogin | D15: 2016 | E15: Dichiarazione ambientale | F15: Aggiornamento 2016 | G15: Ubicazione ufficiale del sito di Trino | H15: 2050 nucleare | I15: Storico / sito | J15: Trino, Piemonte | K15: Nucleare | L15: Coordinate UTM-WGS84 e indirizzo del sito | M15: REVIEWED | N15: CORE | O15: https://www.sogin.it/SiteAssets/uploads/2016/documenti/Dichiarazione_Ambientale_Trino_Aggiornamento_2016.pdf | P15: Coordinate convertite in WGS84: 45.184093 N, 8.277556 E.
A16: S12 | B16: Istruttoria VIA - area Sogin di Borgo Sabotino | C16: Regione Lazio | D16: 2023 | E16: Istruttoria tecnico-amministrativa VIA | F16: 25 agosto 2023 | G16: Ubicazione ufficiale dell'area Sogin di Latina | H16: 2050 nucleare | I16: 2023 | J16: Latina, Lazio | K16: Nucleare / area industriale | L16: Coordinate UTM del centroide dell'area | M16: REVIEWED | N16: CORE | O16: https://regione.lazio.it/sites/default/files/documentazione/AMB-DD-G11375-25-08-2023-Allegato-1.pdf | P16: Coordinate convertite in WGS84: 41.418493 N, 12.809786 E.
... A45: V28-P | B45: MEM v2.8 implementation plan | C45: Stage A checkpoint | D45: 2026 | E45: Markdown | F45: 2026-08-30 | G45: Rules, ranges, QA and limitations | H45: All headline scenarios | I45: 2040/2050 | J45: Workbook-wide | K45: Governance | L45: No material blocker | M45: VERIFIED | N45: CORE | O45: MEM_v2.8_IMPLEMENTATION_PLAN.md | P45: Created before Excel modification.

Sheet 02_SCENARIOS
A1: Controlling scenario matrix — exactly six headline physical scenarios | B1: Controlling scenario matrix — exactly six headline physical scenarios | C1: Controlling scenario matrix — exactly six headline physical scenarios | D1: Controlling scenario matrix — exactly six headline physical scenarios | E1: Controlling scenario matrix — exactly six headline physical scenarios | F1: Controlling scenario matrix — exactly six headline physical scenarios | G1: Controlling scenario matrix — exactly six headline physical scenarios | H1: Controlling scenario matrix — exactly six headline physical scenarios | I1: Controlling scenario matrix — exactly six headline physical scenarios | J1: Controlling scenario matrix — exactly six headline physical scenarios | K1: Controlling scenario matrix — exactly six headline physical scenarios | L1: Controlling scenario matrix — exactly six headline physical scenarios | M1: Controlling scenario matrix — exactly six headline physical scenarios | N1: Controlling scenario matrix — exactly six headline physical scenarios | O1: Controlling scenario matrix — exactly six headline physical scenarios | P1: Controlling scenario matrix — exactly six headline physical scenarios
A2: Scenario multipliers are visible inputs. Slow demand equals Base; High does not accelerate or add RTN projects. | B2: Scenario multipliers are visible inputs. Slow demand equals Base; High does not accelerate or add RTN projects. | C2: Scenario multipliers are visible inputs. Slow demand equals Base; High does not accelerate or add RTN projects. | D2: Scenario multipliers are visible inputs. Slow demand equals Base; High does not accelerate or add RTN projects. | E2: Scenario multipliers are visible inputs. Slow demand equals Base; High does not accelerate or add RTN projects. | F2: Scenario multipliers are visible inputs. Slow demand equals Base; High does not accelerate or add RTN projects. | G2: Scenario multipliers are visible inputs. Slow demand equals Base; High does not accelerate or add RTN projects. | H2: Scenario multipliers are visible inputs. Slow demand equals Base; High does not accelerate or add RTN projects. | I2: Scenario multipliers are visible inputs. Slow demand equals Base; High does not accelerate or add RTN projects. | J2: Scenario multipliers are visible inputs. Slow demand equals Base; High does not accelerate or add RTN projects. | K2: Scenario multipliers are visible inputs. Slow demand equals Base; High does not accelerate or add RTN projects. | L2: Scenario multipliers are visible inputs. Slow demand equals Base; High does not accelerate or add RTN projects. | M2: Scenario multipliers are visible inputs. Slow demand equals Base; High does not accelerate or add RTN projects. | N2: Scenario multipliers are visible inputs. Slow demand equals Base; High does not accelerate or add RTN projects. | O2: Scenario multipliers are visible inputs. Slow demand equals Base; High does not accelerate or add RTN projects. | P2: Scenario multipliers are visible inputs. Slow demand equals Base; High does not accelerate or add RTN projects.
A4: Scenario ID | B4: Horizon | C4: Role | D4: National total TWh | E4: Rigid TWh | F4: P2X TWh | G4: Demand mult. | H4: FER mult. | I4: Storage mult. | J4: Internal network | K4: Foreign network | L4: Dispatchable treatment | M4: Nuclear GW | N4: CO2 default EUR2025/t | O4: Class | P4: Key narrative / model boundary
A5: IT2040_SLOW | B5: 2040 | C5: SLOW | D5: =$B$18 -> 439 | E5: =$B$20 -> 411.5 | F5: =$B$19 -> 27.5 | G5: =$B$16 -> 1 | H5: =$B$15 -> 0.8 | I5: =$B$15 -> 0.8 | J5: +2y project delay; delayed COD <=2040 | K5: Approved 2030 directional floor; project delay register; no added overlay MW | L5: 55 GW national thermal envelope; no backfill | M5: =0 -> 0 | N5: =$B$28 -> 104.55 | O5: Derived scenario | P5: Base demand. FER and BESS power/energy -20%. Slow network removes only delayed project effects crossing 2040.
A6: IT2040_BASE | B6: 2040 | C6: BASE | D6: =$B$18 -> 439 | E6: =$B$20 -> 411.5 | F6: =$B$19 -> 27.5 | G6: =$B$16 -> 1 | H6: =$B$16 -> 1 | I6: =$B$16 -> 1 | J6: Approved PdS 2040 directional values | K6: Approved 2030 directional floor / endogenous PyPSA-Eur | L6: 55 GW national thermal envelope | M6: =0 -> 0 | N6: =$B$28 -> 104.55 | O6: Direct + reconciled | P6: DE-IT 2040 base case.
A7: IT2040_HIGH | B7: 2040 | C7: HIGH | D7: =$B$18*$B$17 -> 482.9 | E7: =$B$20*$B$17 -> 452.65 | F7: =$B$19*$B$17 -> 30.25 | G7: =$B$17 -> 1.1 | H7: =$B$17 -> 1.1 | I7: =$B$17 -> 1.1 | J7: Exactly Base; no acceleration | K7: Exactly Base; no acceleration | L7: 55 GW national thermal envelope; no automatic capacity uplift | M7: =0 -> 0 | N7: =$B$28 -> 104.55 | O7: Derived scenario | P7: 10% higher load is accommodated by 10% more FER/storage plus implicit DSO smart-grid, aggregated demand flexibility and local flexibility outside the explicit HV-zonal boundary.
A8: IT2050_SLOW | B8: 2050 | C8: SLOW | D8: =$B$22 -> 583.1 | E8: =$B$24 -> 501.6 | F8: =$B$23 -> 81.5 | G8: =$B$16 -> 1 | H8: =$B$15 -> 0.8 | I8: =$B$15 -> 0.8 | J8: Exactly recomputed IT2040_SLOW network | K8: Approved 2030 directional floor; same as 2040 Slow | L8: >=30 GW approximate all-programmable adequacy floor; no backfill | M8: =$B$27 -> 8 | N8: =$B$29 -> 400 | O8: Derived scenario | P8: Base demand. FER and BESS power/energy -20%. 8 GW nuclear retained; no-nuclear remains an overlay.
A9: IT2050_BASE | B9: 2050 | C9: BASE | D9: =$B$22 -> 583.1 | E9: =$B$24 -> 501.6 | F9: =$B$23 -> 81.5 | G9: =$B$16 -> 1 | H9: =$B$16 -> 1 | I9: =$B$16 -> 1 | J9: Approved PdS 2040 floor | K9: Approved 2030 directional floor / endogenous PyPSA-Eur | L9: >=30 GW approximate all-programmable adequacy floor | M9: =$B$27 -> 8 | N9: =$B$29 -> 400 | O9: Direct + bridge | P9: PNIEC 2050 with 8 GW nuclear base case.
A10: IT2050_HIGH | B10: 2050 | C10: HIGH | D10: =$B$22*$B$17 -> 641.41 | E10: =$B$24*$B$17 -> 551.76 | F10: =$B$23*$B$17 -> 89.65 | G10: =$B$17 -> 1.1 | H10: =$B$17 -> 1.1 | I10: =$B$17 -> 1.1 | J10: Exactly Base; no acceleration | K10: Exactly Base; no acceleration | L10: >=30 GW approximate all-programmable adequacy floor; no automatic capacity uplift | M10: =$B$27 -> 8 | N10: =$B$29 -> 400 | O10: Derived scenario | P10: 10% higher load is not supported by new/accelerated Terna HV build. Extra accommodation is FER/storage plus implicit distribution and aggregated flexibility outside the explicit model boundary.
A13: Visible scenario parameters | B13: Visible scenario parameters | C13: Visible scenario parameters | E13: Secondary benchmarks and overlays — not headline scenarios | F13: Secondary benchmarks and overlays — not headline scenarios | G13: Secondary benchmarks and overlays — not headline scenarios | H13: Secondary benchmarks and overlays — not headline scenarios | I13: Secondary benchmarks and overlays — not headline scenarios | J13: Secondary benchmarks and overlays — not headline scenarios | K13: Secondary benchmarks and overlays — not headline scenarios | L13: Secondary benchmarks and overlays — not headline scenarios | M13: Secondary benchmarks and overlays — not headline scenarios | N13: Secondary benchmarks and overlays — not headline scenarios | O13: Secondary benchmarks and overlays — not headline scenarios | P13: Secondary benchmarks and overlays — not headline scenarios
A14: Parameter | B14: Value | C14: Use / evidence | E14: Overlay / benchmark | F14: Status | G14: Use
A15: Slow multiplier | B15: 0.8 | C15: FER and BESS power/energy | E15: GA-IT 2040 | F15: Benchmark | G15: Alternative H2/gas/CCS pathway; not High
A16: Base multiplier | B16: 1 | C16: Base and Slow demand | E16: PNIEC Slow 2040 | F16: Benchmark | G16: Evidence reference; not the formula-defined headline Slow
A17: High multiplier | B17: 1.1 | C17: Demand, FER and BESS power/energy | E17: No-nuclear 2050 | F17: Overlay | G17: Counterfactual only
A18: 2040 national total TWh | B18: 439 | C18: DDS DE-IT direct | E18: CO2 175/400/550/1000 | F18: Overlay | G18: Independent market sensitivity
A19: 2040 P2X TWh | B19: 27.5 | C19: DDS direct | E19: Nuclear availability 90.8/92.45/93.4% | F19: Overlay | G19: Independent operating sensitivity
A20: 2040 rigid TWh — reconciled | B20: =B18-B19 -> 411.5 | C20: Total minus P2X; exact arithmetic | E20: Weather / dunkelflaute | F20: Overlay | G20: Independent weather sensitivity
A21: 2040 rigid TWh — legacy rounded | B21: 412 | C21: Reference only; not used in formulas
A22: 2050 national total TWh | B22: 583.1 | C22: PNIEC/Terna direct
A23: 2050 P2X TWh | B23: 81.5 | C23: PNIEC/Terna direct
A24: 2050 rigid TWh | B24: =B22-B23 -> 501.6 | C24: Total minus P2X
A25: 2040 thermal envelope GW | B25: 55 | C25: DDS direct approximate
A26: 2050 programmable floor GW | B26: 30 | C26: Terna derived approximate minimum
A27: 2050 nuclear GW | B27: 8 | C27: PNIEC direct
A28: 2040 CO2 default | B28: 104.55 | C28: Existing v2.7 base
A29: 2050 CO2 default | B29: 400 | C29: Existing v2.7 base

Sheet 03_ZONE_MAP
A1: Crosswalk geografico
A2: Regioni e aree assegnate alle zone di mercato e ai bus canonici PyPSA.
A4: Record ID | B4: Tipo record | C4: Regione/area | D4: Tipo unità | E4: Codice zona | F4: Zona | G4: Bus PyPSA | H4: Validità | I4: Status | J4: Affidabilità | K4: Regola assegnazione | L4: Fonte | M4: URL fonte | N4: Note
A5: GEO-001 | B5: Region-to-market-zone | C5: Valle d'Aosta | D5: Region | E5: NORD | F5: Nord | G5: IT_NORD | H5: 2021-01-01 | I5: Current official association | J5: A — Official Terna A.24 | K5: Direct region association; plant/load coordinates and official zone code override any coarse aggregation | L5: A24 | M5: https://download.terna.it/terna/Allegato%20A.24%20-%20Individuazione%20zone%20della%20rete%20rilevante_8d8bc86c78365d0.pdf | N5: Spot-market geographic zone; not Capacity Market sub-area.
A6: GEO-002 | B6: Region-to-market-zone | C6: Piemonte | D6: Region | E6: NORD | F6: Nord | G6: IT_NORD | H6: 2021-01-01 | I6: Current official association | J6: A — Official Terna A.24 | K6: Direct region association; plant/load coordinates and official zone code override any coarse aggregation | L6: A24 | M6: https://download.terna.it/terna/Allegato%20A.24%20-%20Individuazione%20zone%20della%20rete%20rilevante_8d8bc86c78365d0.pdf | N6: Spot-market geographic zone; not Capacity Market sub-area.
A7: GEO-003 | B7: Region-to-market-zone | C7: Liguria | D7: Region | E7: NORD | F7: Nord | G7: IT_NORD | H7: 2021-01-01 | I7: Current official association | J7: A — Official Terna A.24 | K7: Direct region association; plant/load coordinates and official zone code override any coarse aggregation | L7: A24 | M7: https://download.terna.it/terna/Allegato%20A.24%20-%20Individuazione%20zone%20della%20rete%20rilevante_8d8bc86c78365d0.pdf | N7: Spot-market geographic zone; not Capacity Market sub-area.
A8: GEO-004 | B8: Region-to-market-zone | C8: Lombardia | D8: Region | E8: NORD | F8: Nord | G8: IT_NORD | H8: 2021-01-01 | I8: Current official association | J8: A — Official Terna A.24 | K8: Direct region association; plant/load coordinates and official zone code override any coarse aggregation | L8: A24 | M8: https://download.terna.it/terna/Allegato%20A.24%20-%20Individuazione%20zone%20della%20rete%20rilevante_8d8bc86c78365d0.pdf | N8: Spot-market geographic zone; not Capacity Market sub-area.
A9: GEO-005 | B9: Region-to-market-zone | C9: Trentino-Alto Adige | D9: Region | E9: NORD | F9: Nord | G9: IT_NORD | H9: 2021-01-01 | I9: Current official association | J9: A — Official Terna A.24 | K9: Direct region association; plant/load coordinates and official zone code override any coarse aggregation | L9: A24 | M9: https://download.terna.it/terna/Allegato%20A.24%20-%20Individuazione%20zone%20della%20rete%20rilevante_8d8bc86c78365d0.pdf | N9: Spot-market geographic zone; not Capacity Market sub-area.
A10: GEO-006 | B10: Region-to-market-zone | C10: Veneto | D10: Region | E10: NORD | F10: Nord | G10: IT_NORD | H10: 2021-01-01 | I10: Current official association | J10: A — Official Terna A.24 | K10: Direct region association; plant/load coordinates and official zone code override any coarse aggregation | L10: A24 | M10: https://download.terna.it/terna/Allegato%20A.24%20-%20Individuazione%20zone%20della%20rete%20rilevante_8d8bc86c78365d0.pdf | N10: Spot-market geographic zone; not Capacity Market sub-area.
A11: GEO-007 | B11: Region-to-market-zone | C11: Friuli-Venezia Giulia | D11: Region | E11: NORD | F11: Nord | G11: IT_NORD | H11: 2021-01-01 | I11: Current official association | J11: A — Official Terna A.24 | K11: Direct region association; plant/load coordinates and official zone code override any coarse aggregation | L11: A24 | M11: https://download.terna.it/terna/Allegato%20A.24%20-%20Individuazione%20zone%20della%20rete%20rilevante_8d8bc86c78365d0.pdf | N11: Spot-market geographic zone; not Capacity Market sub-area.
A12: GEO-008 | B12: Region-to-market-zone | C12: Emilia-Romagna | D12: Region | E12: NORD | F12: Nord | G12: IT_NORD | H12: 2021-01-01 | I12: Current official association | J12: A — Official Terna A.24 | K12: Direct region association; plant/load coordinates and official zone code override any coarse aggregation | L12: A24 | M12: https://download.terna.it/terna/Allegato%20A.24%20-%20Individuazione%20zone%20della%20rete%20rilevante_8d8bc86c78365d0.pdf | N12: Spot-market geographic zone; not Capacity Market sub-area.
A13: GEO-009 | B13: Region-to-market-zone | C13: Toscana | D13: Region | E13: CNOR | F13: Centro Nord | G13: IT_CNOR | H13: 2021-01-01 | I13: Current official association | J13: A — Official Terna A.24 | K13: Direct region association; plant/load coordinates and official zone code override any coarse aggregation | L13: A24 | M13: https://download.terna.it/terna/Allegato%20A.24%20-%20Individuazione%20zone%20della%20rete%20rilevante_8d8bc86c78365d0.pdf | N13: Spot-market geographic zone; not Capacity Market sub-area.
A14: GEO-010 | B14: Region-to-market-zone | C14: Marche | D14: Region | E14: CNOR | F14: Centro Nord | G14: IT_CNOR | H14: 2021-01-01 | I14: Current official association | J14: A — Official Terna A.24 | K14: Direct region association; plant/load coordinates and official zone code override any coarse aggregation | L14: A24 | M14: https://download.terna.it/terna/Allegato%20A.24%20-%20Individuazione%20zone%20della%20rete%20rilevante_8d8bc86c78365d0.pdf | N14: Spot-market geographic zone; not Capacity Market sub-area.
A15: GEO-011 | B15: Region-to-market-zone | C15: Umbria | D15: Region | E15: CSUD | F15: Centro Sud | G15: IT_CSUD | H15: 2021-01-01 | I15: Current official association | J15: A — Official Terna A.24 | K15: Direct region association; plant/load coordinates and official zone code override any coarse aggregation | L15: A24 | M15: https://download.terna.it/terna/Allegato%20A.24%20-%20Individuazione%20zone%20della%20rete%20rilevante_8d8bc86c78365d0.pdf | N15: Spot-market geographic zone; not Capacity Market sub-area.
... A34: GEO-030 | B34: Foreign bidding area | C34: Tunisia | D34: Country / virtual zone | E34: TN | F34: Tunisia — future | G34: TN | H34: Current / project-specific | I34: External/virtual modelling node | J34: A/B | K34: Use endogenous PyPSA-Eur bus where represented; otherwise collapsed external bus with explicit price/import assumption | L34: S01 / S09 | M34: https://download.terna.it/terna/Terna_Piano_Sviluppo_2025_Stato_sistema_elettrico_scenari_energetici_8dd62ec4bbb9f75.pdf | N34: Not an Italian geographic bidding zone.

Sheet 04_GENERATION_BY_ZONE
A1: Generation capacity by zone — Slow / Base / High | B1: Generation capacity by zone — Slow / Base / High | C1: Generation capacity by zone — Slow / Base / High | D1: Generation capacity by zone — Slow / Base / High | E1: Generation capacity by zone — Slow / Base / High | F1: Generation capacity by zone — Slow / Base / High | G1: Generation capacity by zone — Slow / Base / High | H1: Generation capacity by zone — Slow / Base / High | I1: Generation capacity by zone — Slow / Base / High | J1: Generation capacity by zone — Slow / Base / High | K1: Generation capacity by zone — Slow / Base / High
A2: FER is formula-driven at 0.80 / 1.00 / 1.10. Nuclear remains 0 GW in 2040 and 8 GW in all 2050 headline cases. Dispatchable national controls are separated from absent zonal allocations. | B2: FER is formula-driven at 0.80 / 1.00 / 1.10. Nuclear remains 0 GW in 2040 and 8 GW in all 2050 headline cases. Dispatchable national controls are separated from absent zonal allocations. | C2: FER is formula-driven at 0.80 / 1.00 / 1.10. Nuclear remains 0 GW in 2040 and 8 GW in all 2050 headline cases. Dispatchable national controls are separated from absent zonal allocations. | D2: FER is formula-driven at 0.80 / 1.00 / 1.10. Nuclear remains 0 GW in 2040 and 8 GW in all 2050 headline cases. Dispatchable national controls are separated from absent zonal allocations. | E2: FER is formula-driven at 0.80 / 1.00 / 1.10. Nuclear remains 0 GW in 2040 and 8 GW in all 2050 headline cases. Dispatchable national controls are separated from absent zonal allocations. | F2: FER is formula-driven at 0.80 / 1.00 / 1.10. Nuclear remains 0 GW in 2040 and 8 GW in all 2050 headline cases. Dispatchable national controls are separated from absent zonal allocations. | G2: FER is formula-driven at 0.80 / 1.00 / 1.10. Nuclear remains 0 GW in 2040 and 8 GW in all 2050 headline cases. Dispatchable national controls are separated from absent zonal allocations. | H2: FER is formula-driven at 0.80 / 1.00 / 1.10. Nuclear remains 0 GW in 2040 and 8 GW in all 2050 headline cases. Dispatchable national controls are separated from absent zonal allocations. | I2: FER is formula-driven at 0.80 / 1.00 / 1.10. Nuclear remains 0 GW in 2040 and 8 GW in all 2050 headline cases. Dispatchable national controls are separated from absent zonal allocations. | J2: FER is formula-driven at 0.80 / 1.00 / 1.10. Nuclear remains 0 GW in 2040 and 8 GW in all 2050 headline cases. Dispatchable national controls are separated from absent zonal allocations. | K2: FER is formula-driven at 0.80 / 1.00 / 1.10. Nuclear remains 0 GW in 2040 and 8 GW in all 2050 headline cases. Dispatchable national controls are separated from absent zonal allocations.
A4: Zone | B4: Technology | C4: 2040 Slow GW | D4: 2040 Base GW | E4: 2040 High GW | F4: 2050 Slow GW | G4: 2050 Base GW | H4: 2050 High GW | I4: Evidence | J4: Class | K4: Zonal allocation flag
A5: NORD | B5: Solar rooftop / distributed | C5: =D5*'02_SCENARIOS'!$H$5 -> 20.08 | D5: 25.1 | E5: =D5*'02_SCENARIOS'!$H$7 -> 27.61 | F5: =G5*'02_SCENARIOS'!$H$8 -> 40.691481 | G5: 50.864351 | H5: =G5*'02_SCENARIOS'!$H$10 -> 55.950786 | I5: v2.7 Base; DDS/PNIEC national controls | J5: Direct national / inherited zonal proxy | K5: USER DECISION: v2.7 zonal allocation retained
A6: NORD | B6: Solar utility | C6: =D6*'02_SCENARIOS'!$H$5 -> 13.84 | D6: 17.3 | E6: =D6*'02_SCENARIOS'!$H$7 -> 19.03 | F6: =G6*'02_SCENARIOS'!$H$8 -> 28.046319 | G6: 35.057899 | H6: =G6*'02_SCENARIOS'!$H$10 -> 38.563689 | I6: v2.7 Base; DDS/PNIEC national controls | J6: Direct national / inherited zonal proxy | K6: USER DECISION: v2.7 zonal allocation retained
A7: NORD | B7: Wind onshore | C7: =D7*'02_SCENARIOS'!$H$5 -> 0.48 | D7: 0.6 | E7: =D7*'02_SCENARIOS'!$H$7 -> 0.66 | F7: =G7*'02_SCENARIOS'!$H$8 -> 0.50674487 | G7: 0.63343109 | H7: =G7*'02_SCENARIOS'!$H$10 -> 0.69677419 | I7: v2.7 Base; DDS/PNIEC national controls | J7: Direct national / inherited zonal proxy | K7: USER DECISION: v2.7 zonal allocation retained
A8: NORD | B8: Wind offshore | C8: =D8*'02_SCENARIOS'!$H$5 -> 1.2 | D8: 1.5 | E8: =D8*'02_SCENARIOS'!$H$7 -> 1.65 | F8: =G8*'02_SCENARIOS'!$H$8 -> 1.1842105 | G8: 1.4802632 | H8: =G8*'02_SCENARIOS'!$H$10 -> 1.6282895 | I8: v2.7 Base; DDS/PNIEC national controls | J8: Direct national / inherited zonal proxy | K8: USER DECISION: v2.7 zonal allocation retained
A9: NORD | B9: Nuclear | C9: =D9 -> 0 | D9: 0 | E9: =D9 -> 0 | F9: =G9 -> 5 | G9: 5 | H9: =G9 -> 5 | I9: PNIEC 8 GW; approved 5 NORD / 3 CSUD | J9: Direct national + approved project allocation | K9: APPROVED
A10: CNOR | B10: Solar rooftop / distributed | C10: =D10*'02_SCENARIOS'!$H$5 -> 2.64 | D10: 3.3 | E10: =D10*'02_SCENARIOS'!$H$7 -> 3.63 | F10: =G10*'02_SCENARIOS'!$H$8 -> 5.3498759 | G10: 6.6873449 | H10: =G10*'02_SCENARIOS'!$H$10 -> 7.3560794 | I10: v2.7 Base; DDS/PNIEC national controls | J10: Direct national / inherited zonal proxy | K10: USER DECISION: v2.7 zonal allocation retained
A11: CNOR | B11: Solar utility | C11: =D11*'02_SCENARIOS'!$H$5 -> 5.04 | D11: 6.3 | E11: =D11*'02_SCENARIOS'!$H$7 -> 6.93 | F11: =G11*'02_SCENARIOS'!$H$8 -> 10.2134 | G11: 12.766749 | H11: =G11*'02_SCENARIOS'!$H$10 -> 14.043424 | I11: v2.7 Base; DDS/PNIEC national controls | J11: Direct national / inherited zonal proxy | K11: USER DECISION: v2.7 zonal allocation retained
A12: CNOR | B12: Wind onshore | C12: =D12*'02_SCENARIOS'!$H$5 -> 0.32 | D12: 0.4 | E12: =D12*'02_SCENARIOS'!$H$7 -> 0.44 | F12: =G12*'02_SCENARIOS'!$H$8 -> 0.33782991 | G12: 0.42228739 | H12: =G12*'02_SCENARIOS'!$H$10 -> 0.46451613 | I12: v2.7 Base; DDS/PNIEC national controls | J12: Direct national / inherited zonal proxy | K12: USER DECISION: v2.7 zonal allocation retained
A13: CNOR | B13: Wind offshore | C13: =D13*'02_SCENARIOS'!$H$5 -> 0.64 | D13: 0.8 | E13: =D13*'02_SCENARIOS'!$H$7 -> 0.88 | F13: =G13*'02_SCENARIOS'!$H$8 -> 0.63157895 | G13: 0.78947368 | H13: =G13*'02_SCENARIOS'!$H$10 -> 0.86842105 | I13: v2.7 Base; DDS/PNIEC national controls | J13: Direct national / inherited zonal proxy | K13: USER DECISION: v2.7 zonal allocation retained
A14: CNOR | B14: Nuclear | C14: =D14 -> 0 | D14: 0 | E14: =D14 -> 0 | F14: =G14 -> 0 | G14: 0 | H14: =G14 -> 0 | I14: PNIEC 8 GW; approved 5 NORD / 3 CSUD | J14: Direct national + approved project allocation | K14: APPROVED
A15: CSUD | B15: Solar rooftop / distributed | C15: =D15*'02_SCENARIOS'!$H$5 -> 4.4 | D15: 5.5 | E15: =D15*'02_SCENARIOS'!$H$7 -> 6.05 | F15: =G15*'02_SCENARIOS'!$H$8 -> 8.9164599 | G15: 11.145575 | H15: =G15*'02_SCENARIOS'!$H$10 -> 12.260132 | I15: v2.7 Base; DDS/PNIEC national controls | J15: Direct national / inherited zonal proxy | K15: USER DECISION: v2.7 zonal allocation retained
A16: CSUD | B16: Solar utility | C16: =D16*'02_SCENARIOS'!$H$5 -> 11.68 | D16: 14.6 | E16: =D16*'02_SCENARIOS'!$H$7 -> 16.06 | F16: =G16*'02_SCENARIOS'!$H$8 -> 23.669148 | G16: 29.586435 | H16: =G16*'02_SCENARIOS'!$H$10 -> 32.545079 | I16: v2.7 Base; DDS/PNIEC national controls | J16: Direct national / inherited zonal proxy | K16: USER DECISION: v2.7 zonal allocation retained
A17: CSUD | B17: Wind onshore | C17: =D17*'02_SCENARIOS'!$H$5 -> 5.44 | D17: 6.8 | E17: =D17*'02_SCENARIOS'!$H$7 -> 7.48 | F17: =G17*'02_SCENARIOS'!$H$8 -> 5.7431085 | G17: 7.1788856 | H17: =G17*'02_SCENARIOS'!$H$10 -> 7.8967742 | I17: v2.7 Base; DDS/PNIEC national controls | J17: Direct national / inherited zonal proxy | K17: USER DECISION: v2.7 zonal allocation retained
A18: CSUD | B18: Wind offshore | C18: =D18*'02_SCENARIOS'!$H$5 -> 1.28 | D18: 1.6 | E18: =D18*'02_SCENARIOS'!$H$7 -> 1.76 | F18: =G18*'02_SCENARIOS'!$H$8 -> 1.2631579 | G18: 1.5789474 | H18: =G18*'02_SCENARIOS'!$H$10 -> 1.7368421 | I18: v2.7 Base; DDS/PNIEC national controls | J18: Direct national / inherited zonal proxy | K18: USER DECISION: v2.7 zonal allocation retained
A19: CSUD | B19: Nuclear | C19: =D19 -> 0 | D19: 0 | E19: =D19 -> 0 | F19: =G19 -> 3 | G19: 3 | H19: =G19 -> 3 | I19: PNIEC 8 GW; approved 5 NORD / 3 CSUD | J19: Direct national + approved project allocation | K19: APPROVED
A20: SUD | B20: Solar rooftop / distributed | C20: =D20*'02_SCENARIOS'!$H$5 -> 1.36 | D20: 1.7 | E20: =D20*'02_SCENARIOS'!$H$7 -> 1.87 | F20: =G20*'02_SCENARIOS'!$H$8 -> 2.7559967 | G20: 3.4449959 | H20: =G20*'02_SCENARIOS'!$H$10 -> 3.7894955 | I20: v2.7 Base; DDS/PNIEC national controls | J20: Direct national / inherited zonal proxy | K20: USER DECISION: v2.7 zonal allocation retained
A21: SUD | B21: Solar utility | C21: =D21*'02_SCENARIOS'!$H$5 -> 15.44 | D21: 19.3 | E21: =D21*'02_SCENARIOS'!$H$7 -> 21.23 | F21: =G21*'02_SCENARIOS'!$H$8 -> 31.288668 | G21: 39.110835 | H21: =G21*'02_SCENARIOS'!$H$10 -> 43.021919 | I21: v2.7 Base; DDS/PNIEC national controls | J21: Direct national / inherited zonal proxy | K21: USER DECISION: v2.7 zonal allocation retained
A22: SUD | B22: Wind onshore | C22: =D22*'02_SCENARIOS'!$H$5 -> 10.56 | D22: 13.2 | E22: =D22*'02_SCENARIOS'!$H$7 -> 14.52 | F22: =G22*'02_SCENARIOS'!$H$8 -> 11.148387 | G22: 13.935484 | H22: =G22*'02_SCENARIOS'!$H$10 -> 15.329032 | I22: v2.7 Base; DDS/PNIEC national controls | J22: Direct national / inherited zonal proxy | K22: USER DECISION: v2.7 zonal allocation retained
A23: SUD | B23: Wind offshore | C23: =D23*'02_SCENARIOS'!$H$5 -> 3.76 | D23: 4.7 | E23: =D23*'02_SCENARIOS'!$H$7 -> 5.17 | F23: =G23*'02_SCENARIOS'!$H$8 -> 3.7105263 | G23: 4.6381579 | H23: =G23*'02_SCENARIOS'!$H$10 -> 5.1019737 | I23: v2.7 Base; DDS/PNIEC national controls | J23: Direct national / inherited zonal proxy | K23: USER DECISION: v2.7 zonal allocation retained
A24: SUD | B24: Nuclear | C24: =D24 -> 0 | D24: 0 | E24: =D24 -> 0 | F24: =G24 -> 0 | G24: 0 | H24: =G24 -> 0 | I24: PNIEC 8 GW; approved 5 NORD / 3 CSUD | J24: Direct national + approved project allocation | K24: APPROVED
A25: CALA | B25: Solar rooftop / distributed | C25: =D25*'02_SCENARIOS'!$H$5 -> 0.88 | D25: 1.1 | E25: =D25*'02_SCENARIOS'!$H$7 -> 1.21 | F25: =G25*'02_SCENARIOS'!$H$8 -> 1.783292 | G25: 2.229115 | H25: =G25*'02_SCENARIOS'!$H$10 -> 2.4520265 | I25: v2.7 Base; DDS/PNIEC national controls | J25: Direct national / inherited zonal proxy | K25: USER DECISION: v2.7 zonal allocation retained
A26: CALA | B26: Solar utility | C26: =D26*'02_SCENARIOS'!$H$5 -> 2 | D26: 2.5 | E26: =D26*'02_SCENARIOS'!$H$7 -> 2.75 | F26: =G26*'02_SCENARIOS'!$H$8 -> 4.0529363 | G26: 5.0661704 | H26: =G26*'02_SCENARIOS'!$H$10 -> 5.5727874 | I26: v2.7 Base; DDS/PNIEC national controls | J26: Direct national / inherited zonal proxy | K26: USER DECISION: v2.7 zonal allocation retained
A27: CALA | B27: Wind onshore | C27: =D27*'02_SCENARIOS'!$H$5 -> 2.64 | D27: 3.3 | E27: =D27*'02_SCENARIOS'!$H$7 -> 3.63 | F27: =G27*'02_SCENARIOS'!$H$8 -> 2.7870968 | G27: 3.483871 | H27: =G27*'02_SCENARIOS'!$H$10 -> 3.8322581 | I27: v2.7 Base; DDS/PNIEC national controls | J27: Direct national / inherited zonal proxy | K27: USER DECISION: v2.7 zonal allocation retained
A28: CALA | B28: Wind offshore | C28: =D28*'02_SCENARIOS'!$H$5 -> 0.48 | D28: 0.6 | E28: =D28*'02_SCENARIOS'!$H$7 -> 0.66 | F28: =G28*'02_SCENARIOS'!$H$8 -> 0.47368421 | G28: 0.59210526 | H28: =G28*'02_SCENARIOS'!$H$10 -> 0.65131579 | I28: v2.7 Base; DDS/PNIEC national controls | J28: Direct national / inherited zonal proxy | K28: USER DECISION: v2.7 zonal allocation retained
A29: CALA | B29: Nuclear | C29: =D29 -> 0 | D29: 0 | E29: =D29 -> 0 | F29: =G29 -> 0 | G29: 0 | H29: =G29 -> 0 | I29: PNIEC 8 GW; approved 5 NORD / 3 CSUD | J29: Direct national + approved project allocation | K29: APPROVED
A30: SICI | B30: Solar rooftop / distributed | C30: =D30*'02_SCENARIOS'!$H$5 -> 2.64 | D30: 3.3 | E30: =D30*'02_SCENARIOS'!$H$7 -> 3.63 | F30: =G30*'02_SCENARIOS'!$H$8 -> 5.3498759 | G30: 6.6873449 | H30: =G30*'02_SCENARIOS'!$H$10 -> 7.3560794 | I30: v2.7 Base; DDS/PNIEC national controls | J30: Direct national / inherited zonal proxy | K30: USER DECISION: v2.7 zonal allocation retained
A31: SICI | B31: Solar utility | C31: =D31*'02_SCENARIOS'!$H$5 -> 9.2 | D31: 11.5 | E31: =D31*'02_SCENARIOS'!$H$7 -> 12.65 | F31: =G31*'02_SCENARIOS'!$H$8 -> 18.643507 | G31: 23.304384 | H31: =G31*'02_SCENARIOS'!$H$10 -> 25.634822 | I31: v2.7 Base; DDS/PNIEC national controls | J31: Direct national / inherited zonal proxy | K31: USER DECISION: v2.7 zonal allocation retained
A32: SICI | B32: Wind onshore | C32: =D32*'02_SCENARIOS'!$H$5 -> 5.04 | D32: 6.3 | E32: =D32*'02_SCENARIOS'!$H$7 -> 6.93 | F32: =G32*'02_SCENARIOS'!$H$8 -> 5.3208211 | G32: 6.6510264 | H32: =G32*'02_SCENARIOS'!$H$10 -> 7.316129 | I32: v2.7 Base; DDS/PNIEC national controls | J32: Direct national / inherited zonal proxy | K32: USER DECISION: v2.7 zonal allocation retained
A33: SICI | B33: Wind offshore | C33: =D33*'02_SCENARIOS'!$H$5 -> 2.4 | D33: 3 | E33: =D33*'02_SCENARIOS'!$H$7 -> 3.3 | F33: =G33*'02_SCENARIOS'!$H$8 -> 2.3684211 | G33: 2.9605263 | H33: =G33*'02_SCENARIOS'!$H$10 -> 3.2565789 | I33: v2.7 Base; DDS/PNIEC national controls | J33: Direct national / inherited zonal proxy | K33: USER DECISION: v2.7 zonal allocation retained
A34: SICI | B34: Nuclear | C34: =D34 -> 0 | D34: 0 | E34: =D34 -> 0 | F34: =G34 -> 0 | G34: 0 | H34: =G34 -> 0 | I34: PNIEC 8 GW; approved 5 NORD / 3 CSUD | J34: Direct national + approved project allocation | K34: APPROVED
A35: SARD | B35: Solar rooftop / distributed | C35: =D35*'02_SCENARIOS'!$H$5 -> 1.36 | D35: 1.7 | E35: =D35*'02_SCENARIOS'!$H$7 -> 1.87 | F35: =G35*'02_SCENARIOS'!$H$8 -> 2.7559967 | G35: 3.4449959 | H35: =G35*'02_SCENARIOS'!$H$10 -> 3.7894955 | I35: v2.7 Base; DDS/PNIEC national controls | J35: Direct national / inherited zonal proxy | K35: USER DECISION: v2.7 zonal allocation retained
A36: SARD | B36: Solar utility | C36: =D36*'02_SCENARIOS'!$H$5 -> 6.16 | D36: 7.7 | E36: =D36*'02_SCENARIOS'!$H$7 -> 8.47 | F36: =G36*'02_SCENARIOS'!$H$8 -> 12.483044 | G36: 15.603805 | H36: =G36*'02_SCENARIOS'!$H$10 -> 17.164185 | I36: v2.7 Base; DDS/PNIEC national controls | J36: Direct national / inherited zonal proxy | K36: USER DECISION: v2.7 zonal allocation retained
A37: SARD | B37: Wind onshore | C37: =D37*'02_SCENARIOS'!$H$5 -> 2.8 | D37: 3.5 | E37: =D37*'02_SCENARIOS'!$H$7 -> 3.85 | F37: =G37*'02_SCENARIOS'!$H$8 -> 2.9560117 | G37: 3.6950147 | H37: =G37*'02_SCENARIOS'!$H$10 -> 4.0645161 | I37: v2.7 Base; DDS/PNIEC national controls | J37: Direct national / inherited zonal proxy | K37: USER DECISION: v2.7 zonal allocation retained
A38: SARD | B38: Wind offshore | C38: =D38*'02_SCENARIOS'!$H$5 -> 2.4 | D38: 3 | E38: =D38*'02_SCENARIOS'!$H$7 -> 3.3 | F38: =G38*'02_SCENARIOS'!$H$8 -> 2.3684211 | G38: 2.9605263 | H38: =G38*'02_SCENARIOS'!$H$10 -> 3.2565789 | I38: v2.7 Base; DDS/PNIEC national controls | J38: Direct national / inherited zonal proxy | K38: USER DECISION: v2.7 zonal allocation retained
A39: SARD | B39: Nuclear | C39: =D39 -> 0 | D39: 0 | E39: =D39 -> 0 | F39: =G39 -> 0 | G39: 0 | H39: =G39 -> 0 | I39: PNIEC 8 GW; approved 5 NORD / 3 CSUD | J39: Direct national + approved project allocation | K39: APPROVED
A41: NATIONAL | B41: FRNP listed total | C41: =SUM(C5,C6,C7,C8,C10,C11,C12,C13,C15,C16,C17,C18,C20,C21,C22,C23,C25,C26,C27,C28,C30,C31,C32,C33,C35,C36,C37,C38) -> 136.16 | D41: =SUM(D5,D6,D7,D8,D10,D11,D12,D13,D15,D16,D17,D18,D20,D21,D22,D23,D25,D26,D27,D28,D30,D31,D32,D33,D35,D36,D37,D38) -> 170.2 | E41: =SUM(E5,E6,E7,E8,E10,E11,E12,E13,E15,E16,E17,E18,E20,E21,E22,E23,E25,E26,E27,E28,E30,E31,E32,E33,E35,E36,E37,E38) -> 187.22 | F41: =SUM(F5,F6,F7,F8,F10,F11,F12,F13,F15,F16,F17,F18,F20,F21,F22,F23,F25,F26,F27,F28,F30,F31,F32,F33,F35,F36,F37,F38) -> 236.8 | G41: =SUM(G5,G6,G7,G8,G10,G11,G12,G13,G15,G16,G17,G18,G20,G21,G22,G23,G25,G26,G27,G28,G30,G31,G32,G33,G35,G36,G37,G38) -> 296 | H41: =SUM(H5,H6,H7,H8,H10,H11,H12,H13,H15,H16,H17,H18,H20,H21,H22,H23,H25,H26,H27,H28,H30,H31,H32,H33,H35,H36,H37,H38) -> 325.6 | I41: Solar + onshore + offshore | J41: Formula | K41: QA
A42: NATIONAL | B42: Nuclear total | C42: =SUM(C9,C14,C19,C24,C29,C34,C39) -> 0 | D42: =SUM(D9,D14,D19,D24,D29,D34,D39) -> 0 | E42: =SUM(E9,E14,E19,E24,E29,E34,E39) -> 0 | F42: =SUM(F9,F14,F19,F24,F29,F34,F39) -> 8 | G42: =SUM(G9,G14,G19,G24,G29,G34,G39) -> 8 | H42: =SUM(H9,H14,H19,H24,H29,H34,H39) -> 8 | I42: 8 GW 2050 | J42: Formula | K42: QA
A43: NATIONAL | B43: Listed total | C43: =C41+C42 -> 136.16 | D43: =D41+D42 -> 170.2 | E43: =E41+E42 -> 187.22 | F43: =F41+F42 -> 244.8 | G43: =G41+G42 -> 304 | H43: =H41+H42 -> 333.6 | I43: FRNP + nuclear | J43: Formula | K43: QA
A45: Zonal dispatchable / programmable capacity — evidence status
A46: Technology | B46: NORD | C46: CNOR | D46: CSUD | E46: SUD | F46: CALA | G46: SICI | H46: SARD | I46: Italy
A47: CCGT non-CHP | B47: 12.027 | C47: 0.453 | D47: 5.571 | E47: 2.157 | F47: 1.582 | G47: 1.548 | H47: 0.036 | I47: =SUM(B47:H47) -> 23.374
A48: CCGT CHP | B48: 10.727 | C48: 1.123 | D48: 0.671 | E48: 2.204 | F48: 1.607 | G48: 1.442 | H48: 0.591 | I48: =SUM(B48:H48) -> 18.365
A49: Gas turbine non-CHP | B49: 0.168 | C49: 0.058 | D49: 0.725 | E49: 0.252 | F49: 0.227 | G49: 0.648 | H49: 0.15 | I49: =SUM(B49:H49) -> 2.228
A50: Gas turbine CHP | B50: 0.741 | C50: 0.459 | D50: 0.105 | E50: 0.025 | F50: 0.006 | G50: 0.056 | H50: 0 | I50: =SUM(B50:H50) -> 1.392
A51: Other thermoelectric conversion techs* | B51: 5.656 | C51: 0.507 | D51: 2.911 | E51: 3.019 | F51: 0.197 | G51: 1.285 | H51: 1.398 | I51: =SUM(B51:H51) -> 14.973
A52: Geothermal | B52: 0 | C52: 0.772 | D52: 0 | E52: 0 | F52: 0 | G52: 0 | H52: 0 | I52: =SUM(B52:H52) -> 0.772
A53: Hydro total ** | B53: 14.715 | C53: 0.623 | D53: 2.33 | E53: 0.225 | F53: 0.833 | G53: 0.134 | H53: 0.463 | I53: =SUM(B53:H53) -> 19.323
A54: Bioenergy | B54: 2.373 | C54: 0.179 | D54: 0.446 | E54: 0.446 | F54: 0.175 | G54: 0.069 | H54: 0.111 | I54: =SUM(B54:H54) -> 3.799
A56: National dispatchable evidence controls | B56: National dispatchable evidence controls | C56: National dispatchable evidence controls | D56: National dispatchable evidence controls | E56: National dispatchable evidence controls | F56: National dispatchable evidence controls | G56: National dispatchable evidence controls | H56: National dispatchable evidence controls | I56: National dispatchable evidence controls | J56: National dispatchable evidence controls | K56: National dispatchable evidence controls
A57: Metric | B57: Unit | C57: 2040 Slow | D57: 2040 Base | E57: 2040 High | F57: 2050 Slow | G57: 2050 Base | H57: 2050 High | I57: Evidence class | J57: Source | K57: Treatment
A58: Aggregate thermoelectric envelope | B58: GW | C58: ='02_SCENARIOS'!$B$25 -> 55 | D58: ='02_SCENARIOS'!$B$25 -> 55 | E58: ='02_SCENARIOS'!$B$25 -> 55 | I58: Direct approximate | J58: DDS 2024 / v2.6 | K58: Constant across 2040; plant/cohort p_nom reconciliation; no thermal backfill
A59: All-programmable adequacy floor | B59: GW | F59: ='02_SCENARIOS'!$B$26 -> 30 | G59: ='02_SCENARIOS'!$B$26 -> 30 | H59: ='02_SCENARIOS'!$B$26 -> 30 | I59: Derived approximate minimum | J59: Terna 2050 p.66 | K59: Constant >=30 GW across 2050; not a gas or non-nuclear exact total
A60: Non-nuclear programmable generation QA | B60: TWh | G60: 22.7 | I60: Derived generation | J60: Terna 2050 p.52 Table 3 | K60: Base annual-output control only; capacity absent
A61: Natural-gas generation QA | B61: TWh | D61: 59 | I61: Direct generation | J61: DDS 2024 p.66 Table 18 | K61: Base annual-output control only; CCGT/OCGT MW split absent
A62: Hydrogen-fired turbine installed capacity | B62: GW | I62: Absent | J62: Sources reviewed | K62: Do not infer MW from hydrogen demand or P2G2P narrative

Sheet 05_STORAGE_BY_ZONE
A1: Battery storage by zone — power, energy, duration and efficiency | B1: Battery storage by zone — power, energy, duration and efficiency | C1: Battery storage by zone — power, energy, duration and efficiency | D1: Battery storage by zone — power, energy, duration and efficiency | E1: Battery storage by zone — power, energy, duration and efficiency | F1: Battery storage by zone — power, energy, duration and efficiency | G1: Battery storage by zone — power, energy, duration and efficiency | H1: Battery storage by zone — power, energy, duration and efficiency | I1: Battery storage by zone — power, energy, duration and efficiency | J1: Battery storage by zone — power, energy, duration and efficiency | K1: Battery storage by zone — power, energy, duration and efficiency | L1: Battery storage by zone — power, energy, duration and efficiency | M1: Battery storage by zone — power, energy, duration and efficiency | N1: Battery storage by zone — power, energy, duration and efficiency | O1: Battery storage by zone — power, energy, duration and efficiency | P1: Battery storage by zone — power, energy, duration and efficiency
A2: Slow and High multiply both charging power, discharging power and energy by 0.80 / 1.10. Duration and one-way/round-trip efficiencies remain unchanged. MACSE is a subset and is not summed twice. | B2: Slow and High multiply both charging power, discharging power and energy by 0.80 / 1.10. Duration and one-way/round-trip efficiencies remain unchanged. MACSE is a subset and is not summed twice. | C2: Slow and High multiply both charging power, discharging power and energy by 0.80 / 1.10. Duration and one-way/round-trip efficiencies remain unchanged. MACSE is a subset and is not summed twice. | D2: Slow and High multiply both charging power, discharging power and energy by 0.80 / 1.10. Duration and one-way/round-trip efficiencies remain unchanged. MACSE is a subset and is not summed twice. | E2: Slow and High multiply both charging power, discharging power and energy by 0.80 / 1.10. Duration and one-way/round-trip efficiencies remain unchanged. MACSE is a subset and is not summed twice. | F2: Slow and High multiply both charging power, discharging power and energy by 0.80 / 1.10. Duration and one-way/round-trip efficiencies remain unchanged. MACSE is a subset and is not summed twice. | G2: Slow and High multiply both charging power, discharging power and energy by 0.80 / 1.10. Duration and one-way/round-trip efficiencies remain unchanged. MACSE is a subset and is not summed twice. | H2: Slow and High multiply both charging power, discharging power and energy by 0.80 / 1.10. Duration and one-way/round-trip efficiencies remain unchanged. MACSE is a subset and is not summed twice. | I2: Slow and High multiply both charging power, discharging power and energy by 0.80 / 1.10. Duration and one-way/round-trip efficiencies remain unchanged. MACSE is a subset and is not summed twice. | J2: Slow and High multiply both charging power, discharging power and energy by 0.80 / 1.10. Duration and one-way/round-trip efficiencies remain unchanged. MACSE is a subset and is not summed twice. | K2: Slow and High multiply both charging power, discharging power and energy by 0.80 / 1.10. Duration and one-way/round-trip efficiencies remain unchanged. MACSE is a subset and is not summed twice. | L2: Slow and High multiply both charging power, discharging power and energy by 0.80 / 1.10. Duration and one-way/round-trip efficiencies remain unchanged. MACSE is a subset and is not summed twice. | M2: Slow and High multiply both charging power, discharging power and energy by 0.80 / 1.10. Duration and one-way/round-trip efficiencies remain unchanged. MACSE is a subset and is not summed twice. | N2: Slow and High multiply both charging power, discharging power and energy by 0.80 / 1.10. Duration and one-way/round-trip efficiencies remain unchanged. MACSE is a subset and is not summed twice. | O2: Slow and High multiply both charging power, discharging power and energy by 0.80 / 1.10. Duration and one-way/round-trip efficiencies remain unchanged. MACSE is a subset and is not summed twice. | P2: Slow and High multiply both charging power, discharging power and energy by 0.80 / 1.10. Duration and one-way/round-trip efficiencies remain unchanged. MACSE is a subset and is not summed twice.
A3: 2040 battery portfolio | B3: 2040 battery portfolio | C3: 2040 battery portfolio | D3: 2040 battery portfolio | E3: 2040 battery portfolio | F3: 2040 battery portfolio | G3: 2040 battery portfolio | H3: 2040 battery portfolio | I3: 2040 battery portfolio | J3: 2040 battery portfolio | K3: 2040 battery portfolio | L3: 2040 battery portfolio | M3: 2040 battery portfolio | N3: 2040 battery portfolio | O3: 2040 battery portfolio | P3: 2040 battery portfolio
A4: Zone | B4: Storage class | C4: Slow charge GW | D4: Slow discharge GW | E4: Slow energy GWh | F4: Base charge GW | G4: Base discharge GW | H4: Base energy GWh | I4: High charge GW | J4: High discharge GW | K4: High energy GWh | L4: Duration h | M4: Eta charge | N4: Eta discharge | O4: Round-trip | P4: Accounting / source
A5: NORD | B5: Small-scale 2h | C5: =F5*'02_SCENARIOS'!$I$5 -> 3.04 | D5: =G5*'02_SCENARIOS'!$I$5 -> 3.04 | E5: =H5*'02_SCENARIOS'!$I$5 -> 6.08 | F5: 3.8 | G5: 3.8 | H5: 7.6 | I5: =F5*'02_SCENARIOS'!$I$7 -> 4.18 | J5: =G5*'02_SCENARIOS'!$I$7 -> 4.18 | K5: =H5*'02_SCENARIOS'!$I$7 -> 8.36 | L5: 2 | M5: 0.9486833 | N5: 0.9486833 | O5: =M5*N5 -> 0.9 | P5: Primary input; v2.7/v2.6
A6: NORD | B6: Small-scale 4h | C6: =F6*'02_SCENARIOS'!$I$5 -> 0.76 | D6: =G6*'02_SCENARIOS'!$I$5 -> 0.76 | E6: =H6*'02_SCENARIOS'!$I$5 -> 3.04 | F6: 0.95 | G6: 0.95 | H6: 3.8 | I6: =F6*'02_SCENARIOS'!$I$7 -> 1.045 | J6: =G6*'02_SCENARIOS'!$I$7 -> 1.045 | K6: =H6*'02_SCENARIOS'!$I$7 -> 4.18 | L6: 4 | M6: 0.9486833 | N6: 0.9486833 | O6: =M6*N6 -> 0.9 | P6: Primary input; v2.7/v2.6
A7: NORD | B7: Capacity Market 4h | C7: =F7*'02_SCENARIOS'!$I$5 -> 0.62 | D7: =G7*'02_SCENARIOS'!$I$5 -> 0.62 | E7: =H7*'02_SCENARIOS'!$I$5 -> 2.48 | F7: 0.775 | G7: 0.775 | H7: 3.1 | I7: =F7*'02_SCENARIOS'!$I$7 -> 0.8525 | J7: =G7*'02_SCENARIOS'!$I$7 -> 0.8525 | K7: =H7*'02_SCENARIOS'!$I$7 -> 3.41 | L7: 4 | M7: 0.9486833 | N7: 0.9486833 | O7: =M7*N7 -> 0.9 | P7: Primary input; v2.7/v2.6
A8: NORD | B8: Utility-scale 8h | C8: =F8*'02_SCENARIOS'!$I$5 -> 0 | D8: =G8*'02_SCENARIOS'!$I$5 -> 0 | E8: =H8*'02_SCENARIOS'!$I$5 -> 0 | F8: 0 | G8: 0 | H8: 0 | I8: =F8*'02_SCENARIOS'!$I$7 -> 0 | J8: =G8*'02_SCENARIOS'!$I$7 -> 0 | K8: =H8*'02_SCENARIOS'!$I$7 -> 0 | L8: 8 | M8: 0.9486833 | N8: 0.9486833 | O8: =M8*N8 -> 0.9 | P8: Primary input; includes MACSE subset where allocated
A9: CNOR | B9: Small-scale 2h | C9: =F9*'02_SCENARIOS'!$I$5 -> 0.45333333 | D9: =G9*'02_SCENARIOS'!$I$5 -> 0.45333333 | E9: =H9*'02_SCENARIOS'!$I$5 -> 0.90666667 | F9: 0.56666667 | G9: 0.56666667 | H9: 1.1333333 | I9: =F9*'02_SCENARIOS'!$I$7 -> 0.62333333 | J9: =G9*'02_SCENARIOS'!$I$7 -> 0.62333333 | K9: =H9*'02_SCENARIOS'!$I$7 -> 1.2466667 | L9: 2 | M9: 0.9486833 | N9: 0.9486833 | O9: =M9*N9 -> 0.9 | P9: Primary input; v2.7/v2.6
A10: CNOR | B10: Small-scale 4h | C10: =F10*'02_SCENARIOS'!$I$5 -> 0.11333333 | D10: =G10*'02_SCENARIOS'!$I$5 -> 0.11333333 | E10: =H10*'02_SCENARIOS'!$I$5 -> 0.45333333 | F10: 0.14166667 | G10: 0.14166667 | H10: 0.56666667 | I10: =F10*'02_SCENARIOS'!$I$7 -> 0.15583333 | J10: =G10*'02_SCENARIOS'!$I$7 -> 0.15583333 | K10: =H10*'02_SCENARIOS'!$I$7 -> 0.62333333 | L10: 4 | M10: 0.9486833 | N10: 0.9486833 | O10: =M10*N10 -> 0.9 | P10: Primary input; v2.7/v2.6
A11: CNOR | B11: Capacity Market 4h | C11: =F11*'02_SCENARIOS'!$I$5 -> 0.02 | D11: =G11*'02_SCENARIOS'!$I$5 -> 0.02 | E11: =H11*'02_SCENARIOS'!$I$5 -> 0.08 | F11: 0.025 | G11: 0.025 | H11: 0.1 | I11: =F11*'02_SCENARIOS'!$I$7 -> 0.0275 | J11: =G11*'02_SCENARIOS'!$I$7 -> 0.0275 | K11: =H11*'02_SCENARIOS'!$I$7 -> 0.11 | L11: 4 | M11: 0.9486833 | N11: 0.9486833 | O11: =M11*N11 -> 0.9 | P11: Primary input; v2.7/v2.6
A12: CNOR | B12: Utility-scale 8h | C12: =F12*'02_SCENARIOS'!$I$5 -> 0.32 | D12: =G12*'02_SCENARIOS'!$I$5 -> 0.32 | E12: =H12*'02_SCENARIOS'!$I$5 -> 2.56 | F12: 0.4 | G12: 0.4 | H12: 3.2 | I12: =F12*'02_SCENARIOS'!$I$7 -> 0.44 | J12: =G12*'02_SCENARIOS'!$I$7 -> 0.44 | K12: =H12*'02_SCENARIOS'!$I$7 -> 3.52 | L12: 8 | M12: 0.9486833 | N12: 0.9486833 | O12: =M12*N12 -> 0.9 | P12: Primary input; includes MACSE subset where allocated
A13: CSUD | B13: Small-scale 2h | C13: =F13*'02_SCENARIOS'!$I$5 -> 0.77333333 | D13: =G13*'02_SCENARIOS'!$I$5 -> 0.77333333 | E13: =H13*'02_SCENARIOS'!$I$5 -> 1.5466667 | F13: 0.96666667 | G13: 0.96666667 | H13: 1.9333333 | I13: =F13*'02_SCENARIOS'!$I$7 -> 1.0633333 | J13: =G13*'02_SCENARIOS'!$I$7 -> 1.0633333 | K13: =H13*'02_SCENARIOS'!$I$7 -> 2.1266667 | L13: 2 | M13: 0.9486833 | N13: 0.9486833 | O13: =M13*N13 -> 0.9 | P13: Primary input; v2.7/v2.6
A14: CSUD | B14: Small-scale 4h | C14: =F14*'02_SCENARIOS'!$I$5 -> 0.19333333 | D14: =G14*'02_SCENARIOS'!$I$5 -> 0.19333333 | E14: =H14*'02_SCENARIOS'!$I$5 -> 0.77333333 | F14: 0.24166667 | G14: 0.24166667 | H14: 0.96666667 | I14: =F14*'02_SCENARIOS'!$I$7 -> 0.26583333 | J14: =G14*'02_SCENARIOS'!$I$7 -> 0.26583333 | K14: =H14*'02_SCENARIOS'!$I$7 -> 1.0633333 | L14: 4 | M14: 0.9486833 | N14: 0.9486833 | O14: =M14*N14 -> 0.9 | P14: Primary input; v2.7/v2.6
A15: CSUD | B15: Capacity Market 4h | C15: =F15*'02_SCENARIOS'!$I$5 -> 0.18 | D15: =G15*'02_SCENARIOS'!$I$5 -> 0.18 | E15: =H15*'02_SCENARIOS'!$I$5 -> 0.72 | F15: 0.225 | G15: 0.225 | H15: 0.9 | I15: =F15*'02_SCENARIOS'!$I$7 -> 0.2475 | J15: =G15*'02_SCENARIOS'!$I$7 -> 0.2475 | K15: =H15*'02_SCENARIOS'!$I$7 -> 0.99 | L15: 4 | M15: 0.9486833 | N15: 0.9486833 | O15: =M15*N15 -> 0.9 | P15: Primary input; v2.7/v2.6
A16: CSUD | B16: Utility-scale 8h | C16: =F16*'02_SCENARIOS'!$I$5 -> 2.23 | D16: =G16*'02_SCENARIOS'!$I$5 -> 2.23 | E16: =H16*'02_SCENARIOS'!$I$5 -> 17.84 | F16: 2.7875 | G16: 2.7875 | H16: 22.3 | I16: =F16*'02_SCENARIOS'!$I$7 -> 3.06625 | J16: =G16*'02_SCENARIOS'!$I$7 -> 3.06625 | K16: =H16*'02_SCENARIOS'!$I$7 -> 24.53 | L16: 8 | M16: 0.9486833 | N16: 0.9486833 | O16: =M16*N16 -> 0.9 | P16: Primary input; includes MACSE subset where allocated
... A32: SARD | B32: Utility-scale 8h | C32: =F32*'02_SCENARIOS'!$I$5 -> 2.03 | D32: =G32*'02_SCENARIOS'!$I$5 -> 2.03 | E32: =H32*'02_SCENARIOS'!$I$5 -> 16.24 | F32: 2.5375 | G32: 2.5375 | H32: 20.3 | I32: =F32*'02_SCENARIOS'!$I$7 -> 2.79125 | J32: =G32*'02_SCENARIOS'!$I$7 -> 2.79125 | K32: =H32*'02_SCENARIOS'!$I$7 -> 22.33 | L32: 8 | M32: 0.9486833 | N32: 0.9486833 | O32: =M32*N32 -> 0.9 | P32: Primary input; includes MACSE subset where allocated
A33: NATIONAL | B33: TOTAL 2040 | C33: =SUM(C5:C32) -> 21.813333 | D33: =SUM(D5:D32) -> 21.813333 | E33: =SUM(E5:E32) -> 133.12 | F33: =SUM(F5:F32) -> 27.266667 | G33: =SUM(G5:G32) -> 27.266667 | H33: =SUM(H5:H32) -> 166.4 | I33: =SUM(I5:I32) -> 29.993333 | J33: =SUM(J5:J32) -> 29.993333 | K33: =SUM(K5:K32) -> 183.04 | M33: 0.9486833 | N33: 0.9486833 | O33: =M33*N33 -> 0.9 | P33: Formula; MACSE not added separately
A36: 2050 battery portfolio | B36: 2050 battery portfolio | C36: 2050 battery portfolio | D36: 2050 battery portfolio | E36: 2050 battery portfolio | F36: 2050 battery portfolio | G36: 2050 battery portfolio | H36: 2050 battery portfolio | I36: 2050 battery portfolio | J36: 2050 battery portfolio | K36: 2050 battery portfolio | L36: 2050 battery portfolio | M36: 2050 battery portfolio | N36: 2050 battery portfolio | O36: 2050 battery portfolio | P36: 2050 battery portfolio
A37: Zone | B37: Storage class | C37: Slow charge GW | D37: Slow discharge GW | E37: Slow energy GWh | F37: Base charge GW | G37: Base discharge GW | H37: Base energy GWh | I37: High charge GW | J37: High discharge GW | K37: High energy GWh | L37: Duration h | M37: Eta charge | N37: Eta discharge | O37: Round-trip | P37: Accounting / source
A38: NORD | B38: BESS portfolio | C38: =F38*'02_SCENARIOS'!$I$8 -> 3.0412944 | D38: =G38*'02_SCENARIOS'!$I$8 -> 3.0412944 | E38: =H38*'02_SCENARIOS'!$I$8 -> 16.558158 | F38: 3.8016179 | G38: 3.8016179 | H38: 20.697698 | I38: =F38*'02_SCENARIOS'!$I$10 -> 4.1817797 | J38: =G38*'02_SCENARIOS'!$I$10 -> 4.1817797 | K38: =H38*'02_SCENARIOS'!$I$10 -> 22.767467 | L38: 5.4444444 | M38: 0.9486833 | N38: 0.9486833 | O38: =M38*N38 -> 0.9 | P38: v2.7 2050 bridge; national 237.667 GWh
A39: CNOR | B39: BESS portfolio | C39: =F39*'02_SCENARIOS'!$I$8 -> 1.0487222 | D39: =G39*'02_SCENARIOS'!$I$8 -> 1.0487222 | E39: =H39*'02_SCENARIOS'!$I$8 -> 5.7097097 | F39: 1.3109027 | G39: 1.3109027 | H39: 7.1371371 | I39: =F39*'02_SCENARIOS'!$I$10 -> 1.441993 | J39: =G39*'02_SCENARIOS'!$I$10 -> 1.441993 | K39: =H39*'02_SCENARIOS'!$I$10 -> 7.8508509 | L39: 5.4444444 | M39: 0.9486833 | N39: 0.9486833 | O39: =M39*N39 -> 0.9 | P39: v2.7 2050 bridge; national 237.667 GWh
A40: CSUD | B40: BESS portfolio | C40: =F40*'02_SCENARIOS'!$I$8 -> 5.4953043 | D40: =G40*'02_SCENARIOS'!$I$8 -> 5.4953043 | E40: =H40*'02_SCENARIOS'!$I$8 -> 29.918879 | F40: 6.8691304 | G40: 6.8691304 | H40: 37.398599 | I40: =F40*'02_SCENARIOS'!$I$10 -> 7.5560434 | J40: =G40*'02_SCENARIOS'!$I$10 -> 7.5560434 | K40: =H40*'02_SCENARIOS'!$I$10 -> 41.138458 | L40: 5.4444444 | M40: 0.9486833 | N40: 0.9486833 | O40: =M40*N40 -> 0.9 | P40: v2.7 2050 bridge; national 237.667 GWh
A41: SUD | B41: BESS portfolio | C41: =F41*'02_SCENARIOS'!$I$8 -> 10.214554 | D41: =G41*'02_SCENARIOS'!$I$8 -> 10.214554 | E41: =H41*'02_SCENARIOS'!$I$8 -> 55.612573 | F41: 12.768193 | G41: 12.768193 | H41: 69.515716 | I41: =F41*'02_SCENARIOS'!$I$10 -> 14.045012 | J41: =G41*'02_SCENARIOS'!$I$10 -> 14.045012 | K41: =H41*'02_SCENARIOS'!$I$10 -> 76.467287 | L41: 5.4444444 | M41: 0.9486833 | N41: 0.9486833 | O41: =M41*N41 -> 0.9 | P41: v2.7 2050 bridge; national 237.667 GWh
A42: CALA | B42: BESS portfolio | C42: =F42*'02_SCENARIOS'!$I$8 -> 2.2652399 | D42: =G42*'02_SCENARIOS'!$I$8 -> 2.2652399 | E42: =H42*'02_SCENARIOS'!$I$8 -> 12.332973 | F42: 2.8315499 | G42: 2.8315499 | H42: 15.416216 | I42: =F42*'02_SCENARIOS'!$I$10 -> 3.1147049 | J42: =G42*'02_SCENARIOS'!$I$10 -> 3.1147049 | K42: =H42*'02_SCENARIOS'!$I$10 -> 16.957838 | L42: 5.4444444 | M42: 0.9486833 | N42: 0.9486833 | O42: =M42*N42 -> 0.9 | P42: v2.7 2050 bridge; national 237.667 GWh
A43: SICI | B43: BESS portfolio | C43: =F43*'02_SCENARIOS'!$I$8 -> 7.8024931 | D43: =G43*'02_SCENARIOS'!$I$8 -> 7.8024931 | E43: =H43*'02_SCENARIOS'!$I$8 -> 42.48024 | F43: 9.7531164 | G43: 9.7531164 | H43: 53.1003 | I43: =F43*'02_SCENARIOS'!$I$10 -> 10.728428 | J43: =G43*'02_SCENARIOS'!$I$10 -> 10.728428 | K43: =H43*'02_SCENARIOS'!$I$10 -> 58.41033 | L43: 5.4444444 | M43: 0.9486833 | N43: 0.9486833 | O43: =M43*N43 -> 0.9 | P43: v2.7 2050 bridge; national 237.667 GWh
A44: SARD | B44: BESS portfolio | C44: =F44*'02_SCENARIOS'!$I$8 -> 5.054841 | D44: =G44*'02_SCENARIOS'!$I$8 -> 5.054841 | E44: =H44*'02_SCENARIOS'!$I$8 -> 27.520801 | F44: 6.3185512 | G44: 6.3185512 | H44: 34.401001 | I44: =F44*'02_SCENARIOS'!$I$10 -> 6.9504063 | J44: =G44*'02_SCENARIOS'!$I$10 -> 6.9504063 | K44: =H44*'02_SCENARIOS'!$I$10 -> 37.841101 | L44: 5.4444444 | M44: 0.9486833 | N44: 0.9486833 | O44: =M44*N44 -> 0.9 | P44: v2.7 2050 bridge; national 237.667 GWh
A45: NATIONAL | B45: TOTAL 2050 | C45: =SUM(C38:C44) -> 34.922449 | D45: =SUM(D38:D44) -> 34.922449 | E45: =SUM(E38:E44) -> 190.13333 | F45: =SUM(F38:F44) -> 43.653061 | G45: =SUM(G38:G44) -> 43.653061 | H45: =SUM(H38:H44) -> 237.66667 | I45: =SUM(I38:I44) -> 48.018367 | J45: =SUM(J38:J44) -> 48.018367 | K45: =SUM(K38:K44) -> 261.43333 | M45: 0.9486833 | N45: 0.9486833 | O45: =M45*N45 -> 0.9 | P45: Formula
A48: NATIONAL | B48: MACSE subset — DO NOT SUM | C48: =F48*'02_SCENARIOS'!$I$5 -> 4.2 | D48: =G48*'02_SCENARIOS'!$I$5 -> 4.2 | E48: =H48*'02_SCENARIOS'!$I$5 -> 33.6 | F48: 5.25 | G48: 5.25 | H48: 42 | I48: =F48*'02_SCENARIOS'!$I$7 -> 5.775 | J48: =G48*'02_SCENARIOS'!$I$7 -> 5.775 | K48: =H48*'02_SCENARIOS'!$I$7 -> 46.2 | L48: 8 | M48: 0.9486833 | N48: 0.9486833 | O48: =M48*N48 -> 0.9 | P48: Subset within 2040 utility-scale portfolio

Sheet 06_DEMAND_BY_ZONE
A1: Demand by zone — authoritative frozen 2025 shares | B1: Demand by zone — authoritative frozen 2025 shares | C1: Demand by zone — authoritative frozen 2025 shares | D1: Demand by zone — authoritative frozen 2025 shares | E1: Demand by zone — authoritative frozen 2025 shares | F1: Demand by zone — authoritative frozen 2025 shares | G1: Demand by zone — authoritative frozen 2025 shares | H1: Demand by zone — authoritative frozen 2025 shares | I1: Demand by zone — authoritative frozen 2025 shares | J1: Demand by zone — authoritative frozen 2025 shares | K1: Demand by zone — authoritative frozen 2025 shares | L1: Demand by zone — authoritative frozen 2025 shares | M1: Demand by zone — authoritative frozen 2025 shares | N1: Demand by zone — authoritative frozen 2025 shares
A2: The same accepted 2025 share is applied to total, rigid and Power-to-X in both horizons and all six headline scenarios. Slow equals Base; High equals Base x1.10. | B2: The same accepted 2025 share is applied to total, rigid and Power-to-X in both horizons and all six headline scenarios. Slow equals Base; High equals Base x1.10. | C2: The same accepted 2025 share is applied to total, rigid and Power-to-X in both horizons and all six headline scenarios. Slow equals Base; High equals Base x1.10. | D2: The same accepted 2025 share is applied to total, rigid and Power-to-X in both horizons and all six headline scenarios. Slow equals Base; High equals Base x1.10. | E2: The same accepted 2025 share is applied to total, rigid and Power-to-X in both horizons and all six headline scenarios. Slow equals Base; High equals Base x1.10. | F2: The same accepted 2025 share is applied to total, rigid and Power-to-X in both horizons and all six headline scenarios. Slow equals Base; High equals Base x1.10. | G2: The same accepted 2025 share is applied to total, rigid and Power-to-X in both horizons and all six headline scenarios. Slow equals Base; High equals Base x1.10. | H2: The same accepted 2025 share is applied to total, rigid and Power-to-X in both horizons and all six headline scenarios. Slow equals Base; High equals Base x1.10. | I2: The same accepted 2025 share is applied to total, rigid and Power-to-X in both horizons and all six headline scenarios. Slow equals Base; High equals Base x1.10. | J2: The same accepted 2025 share is applied to total, rigid and Power-to-X in both horizons and all six headline scenarios. Slow equals Base; High equals Base x1.10. | K2: The same accepted 2025 share is applied to total, rigid and Power-to-X in both horizons and all six headline scenarios. Slow equals Base; High equals Base x1.10. | L2: The same accepted 2025 share is applied to total, rigid and Power-to-X in both horizons and all six headline scenarios. Slow equals Base; High equals Base x1.10. | M2: The same accepted 2025 share is applied to total, rigid and Power-to-X in both horizons and all six headline scenarios. Slow equals Base; High equals Base x1.10. | N2: The same accepted 2025 share is applied to total, rigid and Power-to-X in both horizons and all six headline scenarios. Slow equals Base; High equals Base x1.10.
A3: 2040 | B3: 2040 | C3: 2040 | D3: 2040 | E3: 2040 | F3: 2040 | G3: 2040 | H3: 2040 | I3: 2040 | J3: 2040 | K3: 2040 | L3: 2040 | M3: 2040 | N3: 2040
A4: Source label | B4: Model zone | C4: 2025 TWh | D4: Frozen share | E4: Slow total TWh | F4: Slow rigid TWh | G4: Slow P2X TWh | H4: Base total TWh | I4: Base rigid TWh | J4: Base P2X TWh | K4: High total TWh | L4: High rigid TWh | M4: High P2X TWh | N4: Share provenance
A5: CALA | B5: CALA | C5: 11.1 | D5: 0.03490566 | E5: =F5+G5 -> 15.323585 | F5: ='02_SCENARIOS'!$E$5*$D5 -> 14.363679 | G5: ='02_SCENARIOS'!$F$5*$D5 -> 0.95990566 | H5: =I5+J5 -> 15.323585 | I5: ='02_SCENARIOS'!$E$6*$D5 -> 14.363679 | J5: ='02_SCENARIOS'!$F$6*$D5 -> 0.95990566 | K5: =L5+M5 -> 16.855943 | L5: ='02_SCENARIOS'!$E$7*$D5 -> 15.800047 | M5: ='02_SCENARIOS'!$F$7*$D5 -> 1.0558962 | N5: User-supplied MEM_2025_ZONAL_DEMAND_FROZEN.csv
A6: CNORD | B6: CNOR | C6: 30.2 | D6: 0.094968553 | E6: =F6+G6 -> 41.691195 | F6: ='02_SCENARIOS'!$E$5*$D6 -> 39.07956 | G6: ='02_SCENARIOS'!$F$5*$D6 -> 2.6116352 | H6: =I6+J6 -> 41.691195 | I6: ='02_SCENARIOS'!$E$6*$D6 -> 39.07956 | J6: ='02_SCENARIOS'!$F$6*$D6 -> 2.6116352 | K6: =L6+M6 -> 45.860314 | L6: ='02_SCENARIOS'!$E$7*$D6 -> 42.987516 | M6: ='02_SCENARIOS'!$F$7*$D6 -> 2.8727987 | N6: User-supplied MEM_2025_ZONAL_DEMAND_FROZEN.csv
A7: CSUD | B7: CSUD | C7: 42.9 | D7: 0.13490566 | E7: =F7+G7 -> 59.223585 | F7: ='02_SCENARIOS'!$E$5*$D7 -> 55.513679 | G7: ='02_SCENARIOS'!$F$5*$D7 -> 3.7099057 | H7: =I7+J7 -> 59.223585 | I7: ='02_SCENARIOS'!$E$6*$D7 -> 55.513679 | J7: ='02_SCENARIOS'!$F$6*$D7 -> 3.7099057 | K7: =L7+M7 -> 65.145943 | L7: ='02_SCENARIOS'!$E$7*$D7 -> 61.065047 | M7: ='02_SCENARIOS'!$F$7*$D7 -> 4.0808962 | N7: User-supplied MEM_2025_ZONAL_DEMAND_FROZEN.csv
A8: NORD | B8: NORD | C8: 173.3 | D8: 0.54496855 | E8: =F8+G8 -> 239.24119 | F8: ='02_SCENARIOS'!$E$5*$D8 -> 224.25456 | G8: ='02_SCENARIOS'!$F$5*$D8 -> 14.986635 | H8: =I8+J8 -> 239.24119 | I8: ='02_SCENARIOS'!$E$6*$D8 -> 224.25456 | J8: ='02_SCENARIOS'!$F$6*$D8 -> 14.986635 | K8: =L8+M8 -> 263.16531 | L8: ='02_SCENARIOS'!$E$7*$D8 -> 246.68002 | M8: ='02_SCENARIOS'!$F$7*$D8 -> 16.485299 | N8: User-supplied MEM_2025_ZONAL_DEMAND_FROZEN.csv
A9: SARD | B9: SARD | C9: 8 | D9: 0.025157233 | E9: =F9+G9 -> 11.044025 | F9: ='02_SCENARIOS'!$E$5*$D9 -> 10.352201 | G9: ='02_SCENARIOS'!$F$5*$D9 -> 0.6918239 | H9: =I9+J9 -> 11.044025 | I9: ='02_SCENARIOS'!$E$6*$D9 -> 10.352201 | J9: ='02_SCENARIOS'!$F$6*$D9 -> 0.6918239 | K9: =L9+M9 -> 12.148428 | L9: ='02_SCENARIOS'!$E$7*$D9 -> 11.387421 | M9: ='02_SCENARIOS'!$F$7*$D9 -> 0.76100629 | N9: User-supplied MEM_2025_ZONAL_DEMAND_FROZEN.csv
A10: SICI | B10: SICI | C10: 22.3 | D10: 0.070125786 | E10: =F10+G10 -> 30.78522 | F10: ='02_SCENARIOS'!$E$5*$D10 -> 28.856761 | G10: ='02_SCENARIOS'!$F$5*$D10 -> 1.9284591 | H10: =I10+J10 -> 30.78522 | I10: ='02_SCENARIOS'!$E$6*$D10 -> 28.856761 | J10: ='02_SCENARIOS'!$F$6*$D10 -> 1.9284591 | K10: =L10+M10 -> 33.863742 | L10: ='02_SCENARIOS'!$E$7*$D10 -> 31.742437 | M10: ='02_SCENARIOS'!$F$7*$D10 -> 2.121305 | N10: User-supplied MEM_2025_ZONAL_DEMAND_FROZEN.csv
A11: SUD | B11: SUD | C11: 30.2 | D11: 0.094968553 | E11: =F11+G11 -> 41.691195 | F11: ='02_SCENARIOS'!$E$5*$D11 -> 39.07956 | G11: ='02_SCENARIOS'!$F$5*$D11 -> 2.6116352 | H11: =I11+J11 -> 41.691195 | I11: ='02_SCENARIOS'!$E$6*$D11 -> 39.07956 | J11: ='02_SCENARIOS'!$F$6*$D11 -> 2.6116352 | K11: =L11+M11 -> 45.860314 | L11: ='02_SCENARIOS'!$E$7*$D11 -> 42.987516 | M11: ='02_SCENARIOS'!$F$7*$D11 -> 2.8727987 | N11: User-supplied MEM_2025_ZONAL_DEMAND_FROZEN.csv
A12: TOTAL | B12: ITALY | C12: =SUM(C5:C11) -> 318 | D12: =SUM(D5:D11) -> 1 | E12: =SUM(E5:E11) -> 439 | F12: =SUM(F5:F11) -> 411.5 | G12: =SUM(G5:G11) -> 27.5 | H12: =SUM(H5:H11) -> 439 | I12: =SUM(I5:I11) -> 411.5 | J12: =SUM(J5:J11) -> 27.5 | ... M12: =SUM(M5:M11) -> 30.25 | N12: Formula
A16: 2050 | B16: 2050 | C16: 2050 | D16: 2050 | E16: 2050 | F16: 2050 | G16: 2050 | H16: 2050 | I16: 2050 | J16: 2050 | K16: 2050 | L16: 2050 | M16: 2050 | N16: 2050
A17: Source label | B17: Model zone | C17: 2025 TWh | D17: Frozen share | E17: Slow total TWh | F17: Slow rigid TWh | G17: Slow P2X TWh | H17: Base total TWh | I17: Base rigid TWh | J17: Base P2X TWh | K17: High total TWh | L17: High rigid TWh | M17: High P2X TWh | N17: Share provenance
A18: CALA | B18: CALA | C18: 11.1 | D18: 0.03490566 | E18: =F18+G18 -> 20.353491 | F18: ='02_SCENARIOS'!$E$8*$D18 -> 17.508679 | G18: ='02_SCENARIOS'!$F$8*$D18 -> 2.8448113 | H18: =I18+J18 -> 20.353491 | I18: ='02_SCENARIOS'!$E$9*$D18 -> 17.508679 | J18: ='02_SCENARIOS'!$F$9*$D18 -> 2.8448113 | K18: =L18+M18 -> 22.38884 | L18: ='02_SCENARIOS'!$E$10*$D18 -> 19.259547 | M18: ='02_SCENARIOS'!$F$10*$D18 -> 3.1292925 | N18: User-supplied MEM_2025_ZONAL_DEMAND_FROZEN.csv
A19: CNORD | B19: CNOR | C19: 30.2 | D19: 0.094968553 | E19: =F19+G19 -> 55.376164 | F19: ='02_SCENARIOS'!$E$8*$D19 -> 47.636226 | G19: ='02_SCENARIOS'!$F$8*$D19 -> 7.7399371 | H19: =I19+J19 -> 55.376164 | I19: ='02_SCENARIOS'!$E$9*$D19 -> 47.636226 | J19: ='02_SCENARIOS'!$F$9*$D19 -> 7.7399371 | K19: =L19+M19 -> 60.91378 | L19: ='02_SCENARIOS'!$E$10*$D19 -> 52.399849 | M19: ='02_SCENARIOS'!$F$10*$D19 -> 8.5139308 | N19: User-supplied MEM_2025_ZONAL_DEMAND_FROZEN.csv
A20: CSUD | B20: CSUD | C20: 42.9 | D20: 0.13490566 | E20: =F20+G20 -> 78.663491 | F20: ='02_SCENARIOS'!$E$8*$D20 -> 67.668679 | G20: ='02_SCENARIOS'!$F$8*$D20 -> 10.994811 | H20: =I20+J20 -> 78.663491 | I20: ='02_SCENARIOS'!$E$9*$D20 -> 67.668679 | J20: ='02_SCENARIOS'!$F$9*$D20 -> 10.994811 | K20: =L20+M20 -> 86.52984 | L20: ='02_SCENARIOS'!$E$10*$D20 -> 74.435547 | M20: ='02_SCENARIOS'!$F$10*$D20 -> 12.094292 | N20: User-supplied MEM_2025_ZONAL_DEMAND_FROZEN.csv
A21: NORD | B21: NORD | C21: 173.3 | D21: 0.54496855 | E21: =F21+G21 -> 317.77116 | F21: ='02_SCENARIOS'!$E$8*$D21 -> 273.35623 | G21: ='02_SCENARIOS'!$F$8*$D21 -> 44.414937 | H21: =I21+J21 -> 317.77116 | I21: ='02_SCENARIOS'!$E$9*$D21 -> 273.35623 | J21: ='02_SCENARIOS'!$F$9*$D21 -> 44.414937 | K21: =L21+M21 -> 349.54828 | L21: ='02_SCENARIOS'!$E$10*$D21 -> 300.69185 | M21: ='02_SCENARIOS'!$F$10*$D21 -> 48.856431 | N21: User-supplied MEM_2025_ZONAL_DEMAND_FROZEN.csv
A22: SARD | B22: SARD | C22: 8 | D22: 0.025157233 | E22: =F22+G22 -> 14.669182 | F22: ='02_SCENARIOS'!$E$8*$D22 -> 12.618868 | G22: ='02_SCENARIOS'!$F$8*$D22 -> 2.0503145 | H22: =I22+J22 -> 14.669182 | I22: ='02_SCENARIOS'!$E$9*$D22 -> 12.618868 | J22: ='02_SCENARIOS'!$F$9*$D22 -> 2.0503145 | K22: =L22+M22 -> 16.136101 | L22: ='02_SCENARIOS'!$E$10*$D22 -> 13.880755 | M22: ='02_SCENARIOS'!$F$10*$D22 -> 2.2553459 | N22: User-supplied MEM_2025_ZONAL_DEMAND_FROZEN.csv
A23: SICI | B23: SICI | C23: 22.3 | D23: 0.070125786 | E23: =F23+G23 -> 40.890346 | F23: ='02_SCENARIOS'!$E$8*$D23 -> 35.175094 | G23: ='02_SCENARIOS'!$F$8*$D23 -> 5.7152516 | H23: =I23+J23 -> 40.890346 | I23: ='02_SCENARIOS'!$E$9*$D23 -> 35.175094 | J23: ='02_SCENARIOS'!$F$9*$D23 -> 5.7152516 | K23: =L23+M23 -> 44.979381 | L23: ='02_SCENARIOS'!$E$10*$D23 -> 38.692604 | M23: ='02_SCENARIOS'!$F$10*$D23 -> 6.2867767 | N23: User-supplied MEM_2025_ZONAL_DEMAND_FROZEN.csv
A24: SUD | B24: SUD | C24: 30.2 | D24: 0.094968553 | E24: =F24+G24 -> 55.376164 | F24: ='02_SCENARIOS'!$E$8*$D24 -> 47.636226 | G24: ='02_SCENARIOS'!$F$8*$D24 -> 7.7399371 | H24: =I24+J24 -> 55.376164 | I24: ='02_SCENARIOS'!$E$9*$D24 -> 47.636226 | J24: ='02_SCENARIOS'!$F$9*$D24 -> 7.7399371 | K24: =L24+M24 -> 60.91378 | L24: ='02_SCENARIOS'!$E$10*$D24 -> 52.399849 | M24: ='02_SCENARIOS'!$F$10*$D24 -> 8.5139308 | N24: User-supplied MEM_2025_ZONAL_DEMAND_FROZEN.csv
A25: TOTAL | B25: ITALY | C25: =SUM(C18:C24) -> 318 | D25: =SUM(D18:D24) -> 1 | E25: =SUM(E18:E24) -> 583.1 | F25: =SUM(F18:F24) -> 501.6 | G25: =SUM(G18:G24) -> 81.5 | H25: =SUM(H18:H24) -> 583.1 | I25: =SUM(I18:I24) -> 501.6 | J25: =SUM(J18:J24) -> 81.5 | ... M25: =SUM(M18:M24) -> 89.65 | N25: Formula
A28: 2040 rigid load is calculated as 439.0 - 27.5 = 411.5 TWh so every zonal rigid + P2X value reconciles exactly to the 439.0 TWh direct total. The legacy 412 TWh value is retained only as a rounded reference in 02_SCENARIOS. | B28: 2040 rigid load is calculated as 439.0 - 27.5 = 411.5 TWh so every zonal rigid + P2X value reconciles exactly to the 439.0 TWh direct total. The legacy 412 TWh value is retained only as a rounded reference in 02_SCENARIOS. | C28: 2040 rigid load is calculated as 439.0 - 27.5 = 411.5 TWh so every zonal rigid + P2X value reconciles exactly to the 439.0 TWh direct total. The legacy 412 TWh value is retained only as a rounded reference in 02_SCENARIOS. | D28: 2040 rigid load is calculated as 439.0 - 27.5 = 411.5 TWh so every zonal rigid + P2X value reconciles exactly to the 439.0 TWh direct total. The legacy 412 TWh value is retained only as a rounded reference in 02_SCENARIOS. | E28: 2040 rigid load is calculated as 439.0 - 27.5 = 411.5 TWh so every zonal rigid + P2X value reconciles exactly to the 439.0 TWh direct total. The legacy 412 TWh value is retained only as a rounded reference in 02_SCENARIOS. | F28: 2040 rigid load is calculated as 439.0 - 27.5 = 411.5 TWh so every zonal rigid + P2X value reconciles exactly to the 439.0 TWh direct total. The legacy 412 TWh value is retained only as a rounded reference in 02_SCENARIOS. | G28: 2040 rigid load is calculated as 439.0 - 27.5 = 411.5 TWh so every zonal rigid + P2X value reconciles exactly to the 439.0 TWh direct total. The legacy 412 TWh value is retained only as a rounded reference in 02_SCENARIOS. | H28: 2040 rigid load is calculated as 439.0 - 27.5 = 411.5 TWh so every zonal rigid + P2X value reconciles exactly to the 439.0 TWh direct total. The legacy 412 TWh value is retained only as a rounded reference in 02_SCENARIOS. | I28: 2040 rigid load is calculated as 439.0 - 27.5 = 411.5 TWh so every zonal rigid + P2X value reconciles exactly to the 439.0 TWh direct total. The legacy 412 TWh value is retained only as a rounded reference in 02_SCENARIOS. | J28: 2040 rigid load is calculated as 439.0 - 27.5 = 411.5 TWh so every zonal rigid + P2X value reconciles exactly to the 439.0 TWh direct total. The legacy 412 TWh value is retained only as a rounded reference in 02_SCENARIOS. | K28: 2040 rigid load is calculated as 439.0 - 27.5 = 411.5 TWh so every zonal rigid + P2X value reconciles exactly to the 439.0 TWh direct total. The legacy 412 TWh value is retained only as a rounded reference in 02_SCENARIOS. | L28: 2040 rigid load is calculated as 439.0 - 27.5 = 411.5 TWh so every zonal rigid + P2X value reconciles exactly to the 439.0 TWh direct total. The legacy 412 TWh value is retained only as a rounded reference in 02_SCENARIOS. | M28: 2040 rigid load is calculated as 439.0 - 27.5 = 411.5 TWh so every zonal rigid + P2X value reconciles exactly to the 439.0 TWh direct total. The legacy 412 TWh value is retained only as a rounded reference in 02_SCENARIOS. | N28: 2040 rigid load is calculated as 439.0 - 27.5 = 411.5 TWh so every zonal rigid + P2X value reconciles exactly to the 439.0 TWh direct total. The legacy 412 TWh value is retained only as a rounded reference in 02_SCENARIOS.
A29: 2040 rigid load is calculated as 439.0 - 27.5 = 411.5 TWh so every zonal rigid + P2X value reconciles exactly to the 439.0 TWh direct total. The legacy 412 TWh value is retained only as a rounded reference in 02_SCENARIOS. | B29: 2040 rigid load is calculated as 439.0 - 27.5 = 411.5 TWh so every zonal rigid + P2X value reconciles exactly to the 439.0 TWh direct total. The legacy 412 TWh value is retained only as a rounded reference in 02_SCENARIOS. | C29: 2040 rigid load is calculated as 439.0 - 27.5 = 411.5 TWh so every zonal rigid + P2X value reconciles exactly to the 439.0 TWh direct total. The legacy 412 TWh value is retained only as a rounded reference in 02_SCENARIOS. | D29: 2040 rigid load is calculated as 439.0 - 27.5 = 411.5 TWh so every zonal rigid + P2X value reconciles exactly to the 439.0 TWh direct total. The legacy 412 TWh value is retained only as a rounded reference in 02_SCENARIOS. | E29: 2040 rigid load is calculated as 439.0 - 27.5 = 411.5 TWh so every zonal rigid + P2X value reconciles exactly to the 439.0 TWh direct total. The legacy 412 TWh value is retained only as a rounded reference in 02_SCENARIOS. | F29: 2040 rigid load is calculated as 439.0 - 27.5 = 411.5 TWh so every zonal rigid + P2X value reconciles exactly to the 439.0 TWh direct total. The legacy 412 TWh value is retained only as a rounded reference in 02_SCENARIOS. | G29: 2040 rigid load is calculated as 439.0 - 27.5 = 411.5 TWh so every zonal rigid + P2X value reconciles exactly to the 439.0 TWh direct total. The legacy 412 TWh value is retained only as a rounded reference in 02_SCENARIOS. | H29: 2040 rigid load is calculated as 439.0 - 27.5 = 411.5 TWh so every zonal rigid + P2X value reconciles exactly to the 439.0 TWh direct total. The legacy 412 TWh value is retained only as a rounded reference in 02_SCENARIOS. | I29: 2040 rigid load is calculated as 439.0 - 27.5 = 411.5 TWh so every zonal rigid + P2X value reconciles exactly to the 439.0 TWh direct total. The legacy 412 TWh value is retained only as a rounded reference in 02_SCENARIOS. | J29: 2040 rigid load is calculated as 439.0 - 27.5 = 411.5 TWh so every zonal rigid + P2X value reconciles exactly to the 439.0 TWh direct total. The legacy 412 TWh value is retained only as a rounded reference in 02_SCENARIOS. | K29: 2040 rigid load is calculated as 439.0 - 27.5 = 411.5 TWh so every zonal rigid + P2X value reconciles exactly to the 439.0 TWh direct total. The legacy 412 TWh value is retained only as a rounded reference in 02_SCENARIOS. | L29: 2040 rigid load is calculated as 439.0 - 27.5 = 411.5 TWh so every zonal rigid + P2X value reconciles exactly to the 439.0 TWh direct total. The legacy 412 TWh value is retained only as a rounded reference in 02_SCENARIOS. | M29: 2040 rigid load is calculated as 439.0 - 27.5 = 411.5 TWh so every zonal rigid + P2X value reconciles exactly to the 439.0 TWh direct total. The legacy 412 TWh value is retained only as a rounded reference in 02_SCENARIOS. | N29: 2040 rigid load is calculated as 439.0 - 27.5 = 411.5 TWh so every zonal rigid + P2X value reconciles exactly to the 439.0 TWh direct total. The legacy 412 TWh value is retained only as a rounded reference in 02_SCENARIOS.

Sheet 07_INTERZONAL_BY_ZONE
A1: Internal directional network — Slow / Base / High | B1: Internal directional network — Slow / Base / High | C1: Internal directional network — Slow / Base / High | D1: Internal directional network — Slow / Base / High | E1: Internal directional network — Slow / Base / High | F1: Internal directional network — Slow / Base / High | G1: Internal directional network — Slow / Base / High | H1: Internal directional network — Slow / Base / High | I1: Internal directional network — Slow / Base / High | J1: Internal directional network — Slow / Base / High | K1: Internal directional network — Slow / Base / High | L1: Internal directional network — Slow / Base / High
A2: Base is the approved PdS 2040 directional matrix; High equals Base. Slow subtracts only project effects whose original 2040 COD shifts to 2042. Slow 2050 equals Slow 2040. | B2: Base is the approved PdS 2040 directional matrix; High equals Base. Slow subtracts only project effects whose original 2040 COD shifts to 2042. Slow 2050 equals Slow 2040. | C2: Base is the approved PdS 2040 directional matrix; High equals Base. Slow subtracts only project effects whose original 2040 COD shifts to 2042. Slow 2050 equals Slow 2040. | D2: Base is the approved PdS 2040 directional matrix; High equals Base. Slow subtracts only project effects whose original 2040 COD shifts to 2042. Slow 2050 equals Slow 2040. | E2: Base is the approved PdS 2040 directional matrix; High equals Base. Slow subtracts only project effects whose original 2040 COD shifts to 2042. Slow 2050 equals Slow 2040. | F2: Base is the approved PdS 2040 directional matrix; High equals Base. Slow subtracts only project effects whose original 2040 COD shifts to 2042. Slow 2050 equals Slow 2040. | G2: Base is the approved PdS 2040 directional matrix; High equals Base. Slow subtracts only project effects whose original 2040 COD shifts to 2042. Slow 2050 equals Slow 2040. | H2: Base is the approved PdS 2040 directional matrix; High equals Base. Slow subtracts only project effects whose original 2040 COD shifts to 2042. Slow 2050 equals Slow 2040. | I2: Base is the approved PdS 2040 directional matrix; High equals Base. Slow subtracts only project effects whose original 2040 COD shifts to 2042. Slow 2050 equals Slow 2040. | J2: Base is the approved PdS 2040 directional matrix; High equals Base. Slow subtracts only project effects whose original 2040 COD shifts to 2042. Slow 2050 equals Slow 2040. | K2: Base is the approved PdS 2040 directional matrix; High equals Base. Slow subtracts only project effects whose original 2040 COD shifts to 2042. Slow 2050 equals Slow 2040. | L2: Base is the approved PdS 2040 directional matrix; High equals Base. Slow subtracts only project effects whose original 2040 COD shifts to 2042. Slow 2050 equals Slow 2040.
A4: From | B4: To | C4: Slow 2040 MW | D4: Base 2040 MW | E4: High 2040 MW | F4: Slow 2050 MW | G4: Base 2050 MW | H4: High 2050 MW | I4: Slow delta MW | J4: Excluded delayed project(s) | K4: Evidence / class | L4: Model treatment
A5: NORD | B5: CNOR | C5: =D5-SUMIF($C$35:$C$83,A5&"->"&B5,$I$35:$I$83) -> 6100 | D5: 6100 | E5: =D5 -> 6100 | F5: =C5 -> 6100 | G5: =D5 -> 6100 | H5: =G5 -> 6100 | I5: =C5-D5 -> 0 | J5: — | K5: S03 Figure 3 + delay register; direct Base / derived Slow | L5: Explicit directional PyPSA Link p_nom
A6: CNOR | B6: NORD | C6: =D6-SUMIF($C$35:$C$83,A6&"->"&B6,$I$35:$I$83) -> 5300 | D6: 5300 | E6: =D6 -> 5300 | F6: =C6 -> 5300 | G6: =D6 -> 5300 | H6: =G6 -> 5300 | I6: =C6-D6 -> 0 | J6: — | K6: S03 Figure 3 + delay register; direct Base / derived Slow | L6: Explicit directional PyPSA Link p_nom
A7: CNOR | B7: CSUD | C7: =D7-SUMIF($C$35:$C$83,A7&"->"&B7,$I$35:$I$83) -> 5400 | D7: 5400 | E7: =D7 -> 5400 | F7: =C7 -> 5400 | G7: =D7 -> 5400 | H7: =G7 -> 5400 | I7: =C7-D7 -> 0 | J7: — | K7: S03 Figure 3 + delay register; direct Base / derived Slow | L7: Explicit directional PyPSA Link p_nom
A8: CSUD | B8: CNOR | C8: =D8-SUMIF($C$35:$C$83,A8&"->"&B8,$I$35:$I$83) -> 6100 | D8: 6100 | E8: =D8 -> 6100 | F8: =C8 -> 6100 | G8: =D8 -> 6100 | H8: =G8 -> 6100 | I8: =C8-D8 -> 0 | J8: — | K8: S03 Figure 3 + delay register; direct Base / derived Slow | L8: Explicit directional PyPSA Link p_nom
A9: CSUD | B9: SUD | C9: =D9-SUMIF($C$35:$C$83,A9&"->"&B9,$I$35:$I$83) -> 3900 | D9: 6300 | E9: =D9 -> 6300 | F9: =C9 -> 3900 | G9: =D9 -> 6300 | H9: =G9 -> 6300 | I9: =C9-D9 -> -2400 | J9: 546-P; 563-P | K9: S03 Figure 3 + delay register; direct Base / derived Slow | L9: Explicit directional PyPSA Link p_nom
A10: SUD | B10: CSUD | C10: =D10-SUMIF($C$35:$C$83,A10&"->"&B10,$I$35:$I$83) -> 6700 | D10: 9100 | E10: =D10 -> 9100 | F10: =C10 -> 6700 | G10: =D10 -> 9100 | H10: =G10 -> 9100 | I10: =C10-D10 -> -2400 | J10: 546-P; 563-P | K10: S03 Figure 3 + delay register; direct Base / derived Slow | L10: Explicit directional PyPSA Link p_nom
A11: SUD | B11: CALA | C11: =D11-SUMIF($C$35:$C$83,A11&"->"&B11,$I$35:$I$83) -> 2000 | D11: 4100 | E11: =D11 -> 4100 | F11: =C11 -> 2000 | G11: =D11 -> 4100 | H11: =G11 -> 4100 | I11: =C11-D11 -> -2100 | J11: 563-P | K11: S03 Figure 3 + delay register; direct Base / derived Slow | L11: Explicit directional PyPSA Link p_nom
A12: CALA | B12: SUD | C12: =D12-SUMIF($C$35:$C$83,A12&"->"&B12,$I$35:$I$83) -> 3250 | D12: 5350 | E12: =D12 -> 5350 | F12: =C12 -> 3250 | G12: =D12 -> 5350 | H12: =G12 -> 5350 | I12: =C12-D12 -> -2100 | J12: 563-P | K12: S03 Figure 3 + delay register; direct Base / derived Slow | L12: Explicit directional PyPSA Link p_nom
A13: CALA | B13: SICI | C13: =D13-SUMIF($C$35:$C$83,A13&"->"&B13,$I$35:$I$83) -> 2050 | D13: 4150 | E13: =D13 -> 4150 | F13: =C13 -> 2050 | G13: =D13 -> 4150 | H13: =G13 -> 4150 | I13: =C13-D13 -> -2100 | J13: 563-P | K13: S03 Figure 3 + delay register; direct Base / derived Slow | L13: Explicit directional PyPSA Link p_nom
A14: SICI | B14: CALA | C14: =D14-SUMIF($C$35:$C$83,A14&"->"&B14,$I$35:$I$83) -> 2000 | D14: 4100 | E14: =D14 -> 4100 | F14: =C14 -> 2000 | G14: =D14 -> 4100 | H14: =G14 -> 4100 | I14: =C14-D14 -> -2100 | J14: 563-P | K14: S03 Figure 3 + delay register; direct Base / derived Slow | L14: Explicit directional PyPSA Link p_nom
A15: CSUD | B15: SARD | C15: =D15-SUMIF($C$35:$C$83,A15&"->"&B15,$I$35:$I$83) -> 720 | D15: 1720 | E15: =D15 -> 1720 | F15: =C15 -> 720 | G15: =D15 -> 1720 | H15: =G15 -> 1720 | I15: =C15-D15 -> -1000 | J15: 732-P | K15: S03 Figure 3 + delay register; direct Base / derived Slow | L15: Explicit directional PyPSA Link p_nom
A16: SARD | B16: CSUD | C16: =D16-SUMIF($C$35:$C$83,A16&"->"&B16,$I$35:$I$83) -> 900 | D16: 1900 | E16: =D16 -> 1900 | F16: =C16 -> 900 | G16: =D16 -> 1900 | H16: =G16 -> 1900 | I16: =C16-D16 -> -1000 | J16: 732-P | K16: S03 Figure 3 + delay register; direct Base / derived Slow | L16: Explicit directional PyPSA Link p_nom
... A28: SICI | B28: SARD | C28: =D28-SUMIF($C$35:$C$83,A28&"->"&B28,$I$35:$I$83) -> 1000 | D28: 1000 | E28: =D28 -> 1000 | F28: =C28 -> 1000 | G28: =D28 -> 1000 | H28: =G28 -> 1000 | I28: =C28-D28 -> 0 | J28: — | K28: S03 Figure 3 + delay register; direct Base / derived Slow | L28: Explicit directional PyPSA Link p_nom
A31: Project-effect trace used by Slow formulas | B31: Project-effect trace used by Slow formulas | C31: Project-effect trace used by Slow formulas | D31: Project-effect trace used by Slow formulas | E31: Project-effect trace used by Slow formulas | F31: Project-effect trace used by Slow formulas | G31: Project-effect trace used by Slow formulas | H31: Project-effect trace used by Slow formulas | I31: Project-effect trace used by Slow formulas | J31: Project-effect trace used by Slow formulas | K31: Project-effect trace used by Slow formulas
A34: Project ID | B34: Project | C34: Direction key | D34: Increment MW | E34: Original COD | F34: Slow COD | G34: In Base (1/0) | H34: In Slow (1/0) | I34: Excluded MW | J34: Source | K34: Note
A35: 302-P | B35: Colunga-Calenzano | C35: NORD->CNOR | D35: 500 | E35: 2026 | F35: 2028 | G35: 1 | H35: 1 | I35: =IF(AND(G35=1,H35=0),D35,0) -> 0 | J35: S03/S05
A36: 302-P | B36: Colunga-Calenzano | C36: CNOR->NORD | D36: 500 | E36: 2026 | F36: 2028 | G36: 1 | H36: 1 | I36: =IF(AND(G36=1,H36=0),D36,0) -> 0 | J36: S03/S05
A37: 436-P | B37: Adriatic Link | C37: NORD->CNOR | D37: 600 | E37: 2029 | F37: 2031 | G37: 1 | H37: 1 | I37: =IF(AND(G37=1,H37=0),D37,0) -> 0 | J37: S03/S05
A38: 436-P | B38: Adriatic Link | C38: CNOR->NORD | D38: 1000 | E38: 2029 | F38: 2031 | G38: 1 | H38: 1 | I38: =IF(AND(G38=1,H38=0),D38,0) -> 0 | J38: S03/S05
A39: 447-P | B39: Dorsale Adriatica | C39: NORD->CNOR | D39: 700 | E39: 2033/2034 | F39: 2035/2036 | G39: 1 | H39: 1 | I39: =IF(AND(G39=1,H39=0),D39,0) -> 0 | J39: S03/S05
A40: 447-P | B40: Dorsale Adriatica | C40: CNOR->NORD | D40: 700 | E40: 2033/2034 | F40: 2035/2036 | G40: 1 | H40: 1 | I40: =IF(AND(G40=1,H40=0),D40,0) -> 0 | J40: S03/S05
A41: 447-P | B41: Dorsale Adriatica | C41: NORD->SUD | D41: 2100 | E41: 2033/2034 | F41: 2035/2036 | G41: 1 | H41: 1 | I41: =IF(AND(G41=1,H41=0),D41,0) -> 0 | J41: S03/S05
A42: 447-P | B42: Dorsale Adriatica | C42: SUD->NORD | D42: 2100 | E42: 2033/2034 | F42: 2035/2036 | G42: 1 | H42: 1 | I42: =IF(AND(G42=1,H42=0),D42,0) -> 0 | J42: S03/S05
A43: 432-P | B43: Remove CSUD-CNOR limits | C43: CNOR->CSUD | D43: 400 | E43: 2026 | F43: 2028 | G43: 1 | H43: 1 | I43: =IF(AND(G43=1,H43=0),D43,0) -> 0 | J43: S03/S05
A44: 432-P | B44: Remove CSUD-CNOR limits | C44: CSUD->CNOR | D44: 400 | E44: 2026 | F44: 2028 | G44: 1 | H44: 1 | I44: =IF(AND(G44=1,H44=0),D44,0) -> 0 | J44: S03/S05
A45: 436-P | B45: Adriatic Link | C45: CNOR->CSUD | D45: 1000 | E45: 2029 | F45: 2031 | G45: 1 | H45: 1 | I45: =IF(AND(G45=1,H45=0),D45,0) -> 0 | J45: S03/S05
A46: 436-P | B46: Adriatic Link | C46: CSUD->CNOR | D46: 1000 | E46: 2029 | F46: 2031 | G46: 1 | H46: 1 | I46: =IF(AND(G46=1,H46=0),D46,0) -> 0 | J46: S03/S05
... A49: 356-P | B49: Central Link | C49: CSUD->CNOR | D49: 600 | E49: 2031 | F49: 2033 | G49: 1 | H49: 1 | I49: =IF(AND(G49=1,H49=0),D49,0) -> 0 | J49: S03/S05
A50: 361-N | B50: West Firenze limitation removal | C50: CNOR->CSUD | D50: 200 | E50: 2036 | F50: 2038 | G50: 1 | H50: 1 | I50: =IF(AND(G50=1,H50=0),D50,0) -> 0 | J50: S03/S05 | K50: Still included
A51: 361-N | B51: West Firenze limitation removal | C51: CSUD->CNOR | D51: 200 | E51: 2036 | F51: 2038 | G51: 1 | H51: 1 | I51: =IF(AND(G51=1,H51=0),D51,0) -> 0 | J51: S03/S05 | K51: Still included
A52: 363-N | B52: Lazio-Toscana maximization | C52: CNOR->CSUD | D52: 300 | E52: 2025 | F52: 2027 | G52: 1 | H52: 1 | I52: =IF(AND(G52=1,H52=0),D52,0) -> 0 | J52: S03/S05
A53: 363-N | B53: Lazio-Toscana maximization | C53: CSUD->CNOR | D53: 300 | E53: 2025 | F53: 2027 | G53: 1 | H53: 1 | I53: =IF(AND(G53=1,H53=0),D53,0) -> 0 | J53: S03/S05
A54: 402-P | B54: Foggia-Villanova | C54: SUD->CSUD | D54: 500 | E54: 2029 | F54: 2031 | G54: 1 | H54: 1 | I54: =IF(AND(G54=1,H54=0),D54,0) -> 0 | J54: S03/S05
A55: 402-P | B55: Foggia-Villanova | C55: CSUD->SUD | D55: 500 | E55: 2029 | F55: 2031 | G55: 1 | H55: 1 | I55: =IF(AND(G55=1,H55=0),D55,0) -> 0 | J55: S03/S05
A56: 506-P | B56: Montecorvino-Benevento | C56: SUD->CSUD | D56: 200 | E56: 2032 | F56: 2034 | G56: 1 | H56: 1 | I56: =IF(AND(G56=1,H56=0),D56,0) -> 0 | J56: S03/S05
A57: 506-P | B57: Montecorvino-Benevento | C57: CSUD->SUD | D57: 200 | E57: 2032 | F57: 2034 | G57: 1 | H57: 1 | I57: =IF(AND(G57=1,H57=0),D57,0) -> 0 | J57: S03/S05
A58: 546-P | B58: Aliano-Montecorvino | C58: SUD->CSUD | D58: 300 | E58: 2040 | F58: 2042 | G58: 1 | H58: 0 | I58: =IF(AND(G58=1,H58=0),D58,0) -> 300 | J58: S03/S05 | K58: Crosses cutoff
A59: 546-P | B59: Aliano-Montecorvino | C59: CSUD->SUD | D59: 300 | E59: 2040 | F59: 2042 | G59: 1 | H59: 0 | I59: =IF(AND(G59=1,H59=0),D59,0) -> 300 | J59: S03/S05 | K59: Crosses cutoff
A60: 553-P | B60: North Benevento | C60: CSUD->SUD | D60: 200 | E60: 2035 | F60: 2037 | G60: 1 | H60: 1 | I60: =IF(AND(G60=1,H60=0),D60,0) -> 0 | J60: S03/S05
A61: 563-P | B61: Dorsale Ionica-Tirrenica | C61: SUD->CSUD | D61: 2100 | E61: 2040 | F61: 2042 | G61: 1 | H61: 0 | I61: =IF(AND(G61=1,H61=0),D61,0) -> 2100 | J61: S03/S05 | K61: Crosses cutoff
A62: 563-P | B62: Dorsale Ionica-Tirrenica | C62: CSUD->SUD | D62: 2100 | E62: 2040 | F62: 2042 | G62: 1 | H62: 0 | I62: =IF(AND(G62=1,H62=0),D62,0) -> 2100 | J62: S03/S05 | K62: Crosses cutoff
A63: 447-P | B63: Dorsale Adriatica | C63: SUD->CSUD | D63: 600 | E63: 2033/2034 | F63: 2035/2036 | G63: 1 | H63: 1 | I63: =IF(AND(G63=1,H63=0),D63,0) -> 0 | J63: S03/S05
A64: 447-P | B64: Dorsale Adriatica | C64: CSUD->SUD | D64: 600 | E64: 2033/2034 | F64: 2035/2036 | G64: 1 | H64: 1 | I64: =IF(AND(G64=1,H64=0),D64,0) -> 0 | J64: S03/S05
A65: 723/E-P | B65: Tyrrhenian East | C65: CSUD->SICI | D65: 1000 | E65: 2028 | F65: 2030 | G65: 1 | H65: 1 | I65: =IF(AND(G65=1,H65=0),D65,0) -> 0 | J65: S03/S05
A66: 723/E-P | B66: Tyrrhenian East | C66: SICI->CSUD | D66: 1000 | E66: 2028 | F66: 2030 | G66: 1 | H66: 1 | I66: =IF(AND(G66=1,H66=0),D66,0) -> 0 | J66: S03/S05
A67: 509-P | B67: North Calabria reconfiguration | C67: SUD->CALA | D67: 300 | E67: 2030 effect; 2028/2036 | F67: 2032 effect; 2030/2038 | G67: 1 | H67: 1 | I67: =IF(AND(G67=1,H67=0),D67,0) -> 0 | J67: S03/S05
A68: 509-P | B68: North Calabria reconfiguration | C68: CALA->SUD | D68: 300 | E68: 2030 effect; 2028/2036 | F68: 2032 effect; 2030/2038 | G68: 1 | H68: 1 | I68: =IF(AND(G68=1,H68=0),D68,0) -> 0 | J68: S03/S05
A69: 506-P | B69: Montecorvino-Benevento | C69: CALA->SUD | D69: 600 | E69: 2032 | F69: 2034 | G69: 1 | H69: 1 | I69: =IF(AND(G69=1,H69=0),D69,0) -> 0 | J69: S03/S05 | K69: Directional
A70: 563-P | B70: Dorsale Ionica-Tirrenica | C70: SUD->CALA | D70: 2100 | E70: 2040 | F70: 2042 | G70: 1 | H70: 0 | I70: =IF(AND(G70=1,H70=0),D70,0) -> 2100 | J70: S03/S05 | K70: Crosses cutoff
A71: 563-P | B71: Dorsale Ionica-Tirrenica | C71: CALA->SUD | D71: 2100 | E71: 2040 | F71: 2042 | G71: 1 | H71: 0 | I71: =IF(AND(G71=1,H71=0),D71,0) -> 2100 | J71: S03/S05 | K71: Crosses cutoff
A72: 555-P | B72: Bolano-Annunziata | C72: SICI->CALA | D72: 700 | E72: 2027 | F72: 2029 | G72: 1 | H72: 1 | I72: =IF(AND(G72=1,H72=0),D72,0) -> 0 | J72: S03/S05 | K72: Asymmetric
A73: 555-P | B73: Bolano-Annunziata | C73: CALA->SICI | D73: 500 | E73: 2027 | F73: 2029 | G73: 1 | H73: 1 | I73: =IF(AND(G73=1,H73=0),D73,0) -> 0 | J73: S03/S05 | K73: Asymmetric
A74: 563-P | B74: Dorsale Ionica-Tirrenica | C74: SICI->CALA | D74: 2100 | E74: 2040 | F74: 2042 | G74: 1 | H74: 0 | I74: =IF(AND(G74=1,H74=0),D74,0) -> 2100 | J74: S03/S05 | K74: Crosses cutoff
A75: 563-P | B75: Dorsale Ionica-Tirrenica | C75: CALA->SICI | D75: 2100 | E75: 2040 | F75: 2042 | G75: 1 | H75: 0 | I75: =IF(AND(G75=1,H75=0),D75,0) -> 2100 | J75: S03/S05 | K75: Crosses cutoff
A76: 301-P | B76: SA.CO.I.3 | C76: CNOR->SARD | D76: 100 | E76: 2029 | F76: 2031 | G76: 1 | H76: 1 | I76: =IF(AND(G76=1,H76=0),D76,0) -> 0 | J76: S03/S05 | K76: Embedded through CORS topology
A77: 301-P | B77: SA.CO.I.3 | C77: SARD->CNOR | D77: 100 | E77: 2029 | F77: 2031 | G77: 1 | H77: 1 | I77: =IF(AND(G77=1,H77=0),D77,0) -> 0 | J77: S03/S05 | K77: Embedded through CORS topology
A78: 732-P | B78: Dorsale Sarda | C78: SARD->CSUD | D78: 1000 | E78: 2040 | F78: 2042 | G78: 1 | H78: 0 | I78: =IF(AND(G78=1,H78=0),D78,0) -> 1000 | J78: S03/S05 | K78: Crosses cutoff
A79: 732-P | B79: Dorsale Sarda | C79: CSUD->SARD | D79: 1000 | E79: 2040 | F79: 2042 | G79: 1 | H79: 0 | I79: =IF(AND(G79=1,H79=0),D79,0) -> 1000 | J79: S03/S05 | K79: Crosses cutoff
A80: 723/W-P | B80: Tyrrhenian West | C80: SARD->SICI | D80: 1000 | E80: 2027 | F80: 2029 | G80: 1 | H80: 1 | I80: =IF(AND(G80=1,H80=0),D80,0) -> 0 | J80: S03/S05
A81: 723/W-P | B81: Tyrrhenian West | C81: SICI->SARD | D81: 1000 | E81: 2027 | F81: 2029 | G81: 1 | H81: 1 | I81: =IF(AND(G81=1,H81=0),D81,0) -> 0 | J81: S03/S05
A82: 355-P | B82: Milano-Montalto | C82: NORD->CSUD | D82: 2100 | E82: 2033/2034 | F82: 2035/2036 | G82: 1 | H82: 1 | I82: =IF(AND(G82=1,H82=0),D82,0) -> 0 | J82: S03/S05
A83: 355-P | B83: Milano-Montalto | C83: CSUD->NORD | D83: 2100 | E83: 2033/2034 | F83: 2035/2036 | G83: 1 | H83: 1 | I83: =IF(AND(G83=1,H83=0),D83,0) -> 0 | J83: S03/S05

Sheet 08_FOREIGN_BY_ZONE
A1: Foreign directional exchange capacity — Slow / Base / High | B1: Foreign directional exchange capacity — Slow / Base / High | C1: Foreign directional exchange capacity — Slow / Base / High | D1: Foreign directional exchange capacity — Slow / Base / High | E1: Foreign directional exchange capacity — Slow / Base / High | F1: Foreign directional exchange capacity — Slow / Base / High | G1: Foreign directional exchange capacity — Slow / Base / High | H1: Foreign directional exchange capacity — Slow / Base / High | I1: Foreign directional exchange capacity — Slow / Base / High | J1: Foreign directional exchange capacity — Slow / Base / High | K1: Foreign directional exchange capacity — Slow / Base / High | L1: Foreign directional exchange capacity — Slow / Base / High | M1: Foreign directional exchange capacity — Slow / Base / High | N1: Foreign directional exchange capacity — Slow / Base / High | O1: Foreign directional exchange capacity — Slow / Base / High | P1: Foreign directional exchange capacity — Slow / Base / High | Q1: Foreign directional exchange capacity — Slow / Base / High
A2: The approved DDS 2030 directional exchange totals are the headline floor and remain unchanged. Planned increments are kept separate from endogenous PyPSA-Eur borders and optional manual NTC sensitivities; no double counting. | B2: The approved DDS 2030 directional exchange totals are the headline floor and remain unchanged. Planned increments are kept separate from endogenous PyPSA-Eur borders and optional manual NTC sensitivities; no double counting. | C2: The approved DDS 2030 directional exchange totals are the headline floor and remain unchanged. Planned increments are kept separate from endogenous PyPSA-Eur borders and optional manual NTC sensitivities; no double counting. | D2: The approved DDS 2030 directional exchange totals are the headline floor and remain unchanged. Planned increments are kept separate from endogenous PyPSA-Eur borders and optional manual NTC sensitivities; no double counting. | E2: The approved DDS 2030 directional exchange totals are the headline floor and remain unchanged. Planned increments are kept separate from endogenous PyPSA-Eur borders and optional manual NTC sensitivities; no double counting. | F2: The approved DDS 2030 directional exchange totals are the headline floor and remain unchanged. Planned increments are kept separate from endogenous PyPSA-Eur borders and optional manual NTC sensitivities; no double counting. | G2: The approved DDS 2030 directional exchange totals are the headline floor and remain unchanged. Planned increments are kept separate from endogenous PyPSA-Eur borders and optional manual NTC sensitivities; no double counting. | H2: The approved DDS 2030 directional exchange totals are the headline floor and remain unchanged. Planned increments are kept separate from endogenous PyPSA-Eur borders and optional manual NTC sensitivities; no double counting. | I2: The approved DDS 2030 directional exchange totals are the headline floor and remain unchanged. Planned increments are kept separate from endogenous PyPSA-Eur borders and optional manual NTC sensitivities; no double counting. | J2: The approved DDS 2030 directional exchange totals are the headline floor and remain unchanged. Planned increments are kept separate from endogenous PyPSA-Eur borders and optional manual NTC sensitivities; no double counting. | K2: The approved DDS 2030 directional exchange totals are the headline floor and remain unchanged. Planned increments are kept separate from endogenous PyPSA-Eur borders and optional manual NTC sensitivities; no double counting. | L2: The approved DDS 2030 directional exchange totals are the headline floor and remain unchanged. Planned increments are kept separate from endogenous PyPSA-Eur borders and optional manual NTC sensitivities; no double counting. | M2: The approved DDS 2030 directional exchange totals are the headline floor and remain unchanged. Planned increments are kept separate from endogenous PyPSA-Eur borders and optional manual NTC sensitivities; no double counting. | N2: The approved DDS 2030 directional exchange totals are the headline floor and remain unchanged. Planned increments are kept separate from endogenous PyPSA-Eur borders and optional manual NTC sensitivities; no double counting. | O2: The approved DDS 2030 directional exchange totals are the headline floor and remain unchanged. Planned increments are kept separate from endogenous PyPSA-Eur borders and optional manual NTC sensitivities; no double counting. | P2: The approved DDS 2030 directional exchange totals are the headline floor and remain unchanged. Planned increments are kept separate from endogenous PyPSA-Eur borders and optional manual NTC sensitivities; no double counting. | Q2: The approved DDS 2030 directional exchange totals are the headline floor and remain unchanged. Planned increments are kept separate from endogenous PyPSA-Eur borders and optional manual NTC sensitivities; no double counting.
A4: Counterparty | B4: Direction | C4: Slow 2040 MW | D4: Base 2040 MW | E4: High 2040 MW | F4: Slow 2050 MW | G4: Base 2050 MW | H4: High 2050 MW | I4: Treatment | J4: Source
A5: France | B5: FR->NORD | C5: =D5 -> 4500 | D5: 4500 | E5: =D5 -> 4500 | F5: =C5 -> 4500 | G5: =D5 -> 4500 | H5: =G5 -> 4500 | I5: ENDOGENOUS PYPSA-EUR / QA; optional manual NTC only | J5: DDS 2024 p.34 Figure 11
A6: France | B6: NORD->FR | C6: =D6 -> 2200 | D6: 2200 | E6: =D6 -> 2200 | F6: =C6 -> 2200 | G6: =D6 -> 2200 | H6: =G6 -> 2200 | I6: ENDOGENOUS PYPSA-EUR / QA; optional manual NTC only | J6: DDS 2024 p.34 Figure 11
A7: Switzerland | B7: CH->NORD | C7: =D7 -> 4600 | D7: 4600 | E7: =D7 -> 4600 | F7: =C7 -> 4600 | G7: =D7 -> 4600 | H7: =G7 -> 4600 | I7: ENDOGENOUS PYPSA-EUR / QA; optional manual NTC only | J7: DDS 2024 p.34 Figure 11
A8: Switzerland | B8: NORD->CH | C8: =D8 -> 1900 | D8: 1900 | E8: =D8 -> 1900 | F8: =C8 -> 1900 | G8: =D8 -> 1900 | H8: =G8 -> 1900 | I8: ENDOGENOUS PYPSA-EUR / QA; optional manual NTC only | J8: DDS 2024 p.34 Figure 11
A9: Austria | B9: AT->NORD | C9: =D9 -> 700 | D9: 700 | E9: =D9 -> 700 | F9: =C9 -> 700 | G9: =D9 -> 700 | H9: =G9 -> 700 | I9: ENDOGENOUS PYPSA-EUR / QA; optional manual NTC only | J9: DDS 2024 p.34 Figure 11
A10: Austria | B10: NORD->AT | C10: =D10 -> 300 | D10: 300 | E10: =D10 -> 300 | F10: =C10 -> 300 | G10: =D10 -> 300 | H10: =G10 -> 300 | I10: ENDOGENOUS PYPSA-EUR / QA; optional manual NTC only | J10: DDS 2024 p.34 Figure 11
A11: Slovenia | B11: SI->NORD | C11: =D11 -> 1100 | D11: 1100 | E11: =D11 -> 1100 | F11: =C11 -> 1100 | G11: =D11 -> 1100 | H11: =G11 -> 1100 | I11: ENDOGENOUS PYPSA-EUR / QA; optional manual NTC only | J11: DDS 2024 p.34 Figure 11
A12: Slovenia | B12: NORD->SI | C12: =D12 -> 1200 | D12: 1200 | E12: =D12 -> 1200 | F12: =C12 -> 1200 | G12: =D12 -> 1200 | H12: =G12 -> 1200 | I12: ENDOGENOUS PYPSA-EUR / QA; optional manual NTC only | J12: DDS 2024 p.34 Figure 11
A13: Montenegro | B13: ME->CSUD | C13: =D13 -> 600 | D13: 600 | E13: =D13 -> 600 | F13: =C13 -> 600 | G13: =D13 -> 600 | H13: =G13 -> 600 | I13: ENDOGENOUS PYPSA-EUR / QA; optional manual NTC only | J13: DDS 2024 p.34 Figure 11
A14: Montenegro | B14: CSUD->ME | C14: =D14 -> 600 | D14: 600 | E14: =D14 -> 600 | F14: =C14 -> 600 | G14: =D14 -> 600 | H14: =G14 -> 600 | I14: ENDOGENOUS PYPSA-EUR / QA; optional manual NTC only | J14: DDS 2024 p.34 Figure 11
A15: Greece | B15: GR->SUD | C15: =D15 -> 500 | D15: 500 | E15: =D15 -> 500 | F15: =C15 -> 500 | G15: =D15 -> 500 | H15: =G15 -> 500 | I15: ENDOGENOUS PYPSA-EUR / QA; optional manual NTC only | J15: DDS 2024 p.34 Figure 11
A16: Greece | B16: SUD->GR | C16: =D16 -> 500 | D16: 500 | E16: =D16 -> 500 | F16: =C16 -> 500 | G16: =D16 -> 500 | H16: =G16 -> 500 | I16: ENDOGENOUS PYPSA-EUR / QA; optional manual NTC only | J16: DDS 2024 p.34 Figure 11
... A20: Malta | B20: SICI->MT | C20: =D20 -> 200 | D20: 200 | E20: =D20 -> 200 | F20: =C20 -> 200 | G20: =D20 -> 200 | H20: =G20 -> 200 | I20: ENDOGENOUS PYPSA-EUR / QA; optional manual NTC only | J20: DDS 2024 p.34 Figure 11
A24: Project increments and embedding / timing treatment | B24: Project increments and embedding / timing treatment | C24: Project increments and embedding / timing treatment | D24: Project increments and embedding / timing treatment | E24: Project increments and embedding / timing treatment | F24: Project increments and embedding / timing treatment | G24: Project increments and embedding / timing treatment | H24: Project increments and embedding / timing treatment | I24: Project increments and embedding / timing treatment | J24: Project increments and embedding / timing treatment | K24: Project increments and embedding / timing treatment | L24: Project increments and embedding / timing treatment | M24: Project increments and embedding / timing treatment | N24: Project increments and embedding / timing treatment | O24: Project increments and embedding / timing treatment | P24: Project increments and embedding / timing treatment | Q24: Project increments and embedding / timing treatment
A26: Project ID | B26: Project | C26: Border | D26: Direction | E26: Increment MW | F26: Original COD | G26: Slow COD | H26: Base inclusion | I26: Slow inclusion | J26: Base contribution | K26: Slow contribution | L26: Embedded? | M26: Source | N26: Page | O26: Status | P26: Uncertainty | Q26: Model treatment
A27: 167-P | B27: Valchiavenna | C27: CH | D27: not specified | E27: 1000 | F27: post-2034 | G27: post-2036 | H27: No overlay | I27: Undetermined | J27: 0 | K27: 0 | L27: No | M27: S03/S05 | N27: p.17 | O27: Planning | P27: Vague timing/direction | Q27: Not added
A28: 208-P | B28: Prati di Vizze-Steinach | C28: AT | D28: not specified | E28: 100 | F28: post-2034 | G28: post-2036 | H28: No overlay | I28: Undetermined | J28: 0 | K28: 0 | L28: No | M28: S03/S05 | N28: p.17 | O28: Planned | P28: Vague timing/direction | Q28: Not added
A29: 252-P | B29: Dobbiaco-Austria | C29: AT | D29: not specified | E29: 160 | F29: post-2034 | G29: post-2036 | H29: No overlay | I29: Undetermined | J29: 0 | K29: 0 | L29: No | M29: S03/S05 | N29: p.17 | O29: Planned | P29: Vague timing/direction | Q29: Not added
A30: 204-P | B30: Italy-Austria 220 kV | C30: AT | D30: not specified | E30: 500 | F30: post-2034 | G30: post-2036 | H30: No overlay | I30: Undetermined | J30: 0 | K30: 0 | L30: No | M30: S03/S05 | N30: p.17 | O30: Planning | P30: Vague timing/direction | Q30: Not added
A31: 200-I | B31: Slovenia Phase 1 | C31: SI | D31: not specified | E31: 400 | F31: post-2034 | G31: post-2036 | H31: No overlay | I31: Undetermined | J31: 0 | K31: 0 | L31: No | M31: S03/S05 | N31: p.17 | O31: Authorization | P31: Vague timing/direction | Q31: Not added
A32: 554-P | B32: GRITA 2 | C32: GR | D32: not specified | E32: 1000 | F32: 2033/2035 first; full post-2034 | G32: 2035/2037 first; full post-2036 | H32: No overlay | I32: Undetermined | J32: 0 | K32: 0 | L32: No | M32: S03/S05 | N32: p.17 | O32: Authorization | P32: Full timing/direction unresolved | Q32: Not added
A33: 601-I | B33: ELMED | C33: TN | D33: not specified | E33: 600 | F33: 2028 | G33: 2030 | H33: Embedded | I33: Embedded | J33: 600 | K33: 600 | L33: Yes | M33: S03/S05 + DDS | N33: p.17 / p.34 | O33: Authorized | P33: Single increment direction absent | Q33: Do not add again
A34: 401-S | B34: Montenegro second pole | C34: ME | D34: not specified | E34: 600 | F34: not specified | G34: not specified | H34: No conditional overlay | I34: Undetermined | J34: 0 | K34: 0 | L34: No | M34: S03/S05 | N34: p.17 | O34: Conditional | P34: No COD | Q34: Not added
A35: 3-P | B35: Piemonte-Savoia | C35: FR | D35: FR->NORD | E35: 1200 | F35: 2023 commissioned | G35: unchanged | H35: Embedded | I35: Embedded | J35: 1200 | K35: 1200 | L35: Yes | M35: S05 | N35: p.55 | O35: In service | P35: None | Q35: Do not add again
A36: 3-P | B36: Piemonte-Savoia | C36: FR | D36: NORD->FR | E36: 1000 | F36: 2023 commissioned | G36: unchanged | H36: Embedded | I36: Embedded | J36: 1000 | K36: 1000 | L36: Yes | M36: S05 | N36: p.55 | O36: In service | P36: None | Q36: Do not add again
A39: Foreign Slow/Base/High matrices are therefore identical. This is deliberate: exact 2030 exchange totals are the approved floor, ELMED and Piemonte-Savoia are already embedded, and the remaining increments lack the combination of non-embedded status, directional NTC and cutoff-resolving timing needed for a separate headline addition. | B39: Foreign Slow/Base/High matrices are therefore identical. This is deliberate: exact 2030 exchange totals are the approved floor, ELMED and Piemonte-Savoia are already embedded, and the remaining increments lack the combination of non-embedded status, directional NTC and cutoff-resolving timing needed for a separate headline addition. | C39: Foreign Slow/Base/High matrices are therefore identical. This is deliberate: exact 2030 exchange totals are the approved floor, ELMED and Piemonte-Savoia are already embedded, and the remaining increments lack the combination of non-embedded status, directional NTC and cutoff-resolving timing needed for a separate headline addition. | D39: Foreign Slow/Base/High matrices are therefore identical. This is deliberate: exact 2030 exchange totals are the approved floor, ELMED and Piemonte-Savoia are already embedded, and the remaining increments lack the combination of non-embedded status, directional NTC and cutoff-resolving timing needed for a separate headline addition. | E39: Foreign Slow/Base/High matrices are therefore identical. This is deliberate: exact 2030 exchange totals are the approved floor, ELMED and Piemonte-Savoia are already embedded, and the remaining increments lack the combination of non-embedded status, directional NTC and cutoff-resolving timing needed for a separate headline addition. | F39: Foreign Slow/Base/High matrices are therefore identical. This is deliberate: exact 2030 exchange totals are the approved floor, ELMED and Piemonte-Savoia are already embedded, and the remaining increments lack the combination of non-embedded status, directional NTC and cutoff-resolving timing needed for a separate headline addition. | G39: Foreign Slow/Base/High matrices are therefore identical. This is deliberate: exact 2030 exchange totals are the approved floor, ELMED and Piemonte-Savoia are already embedded, and the remaining increments lack the combination of non-embedded status, directional NTC and cutoff-resolving timing needed for a separate headline addition. | H39: Foreign Slow/Base/High matrices are therefore identical. This is deliberate: exact 2030 exchange totals are the approved floor, ELMED and Piemonte-Savoia are already embedded, and the remaining increments lack the combination of non-embedded status, directional NTC and cutoff-resolving timing needed for a separate headline addition. | I39: Foreign Slow/Base/High matrices are therefore identical. This is deliberate: exact 2030 exchange totals are the approved floor, ELMED and Piemonte-Savoia are already embedded, and the remaining increments lack the combination of non-embedded status, directional NTC and cutoff-resolving timing needed for a separate headline addition. | J39: Foreign Slow/Base/High matrices are therefore identical. This is deliberate: exact 2030 exchange totals are the approved floor, ELMED and Piemonte-Savoia are already embedded, and the remaining increments lack the combination of non-embedded status, directional NTC and cutoff-resolving timing needed for a separate headline addition. | K39: Foreign Slow/Base/High matrices are therefore identical. This is deliberate: exact 2030 exchange totals are the approved floor, ELMED and Piemonte-Savoia are already embedded, and the remaining increments lack the combination of non-embedded status, directional NTC and cutoff-resolving timing needed for a separate headline addition. | L39: Foreign Slow/Base/High matrices are therefore identical. This is deliberate: exact 2030 exchange totals are the approved floor, ELMED and Piemonte-Savoia are already embedded, and the remaining increments lack the combination of non-embedded status, directional NTC and cutoff-resolving timing needed for a separate headline addition. | M39: Foreign Slow/Base/High matrices are therefore identical. This is deliberate: exact 2030 exchange totals are the approved floor, ELMED and Piemonte-Savoia are already embedded, and the remaining increments lack the combination of non-embedded status, directional NTC and cutoff-resolving timing needed for a separate headline addition. | N39: Foreign Slow/Base/High matrices are therefore identical. This is deliberate: exact 2030 exchange totals are the approved floor, ELMED and Piemonte-Savoia are already embedded, and the remaining increments lack the combination of non-embedded status, directional NTC and cutoff-resolving timing needed for a separate headline addition. | O39: Foreign Slow/Base/High matrices are therefore identical. This is deliberate: exact 2030 exchange totals are the approved floor, ELMED and Piemonte-Savoia are already embedded, and the remaining increments lack the combination of non-embedded status, directional NTC and cutoff-resolving timing needed for a separate headline addition. | P39: Foreign Slow/Base/High matrices are therefore identical. This is deliberate: exact 2030 exchange totals are the approved floor, ELMED and Piemonte-Savoia are already embedded, and the remaining increments lack the combination of non-embedded status, directional NTC and cutoff-resolving timing needed for a separate headline addition. | Q39: Foreign Slow/Base/High matrices are therefore identical. This is deliberate: exact 2030 exchange totals are the approved floor, ELMED and Piemonte-Savoia are already embedded, and the remaining increments lack the combination of non-embedded status, directional NTC and cutoff-resolving timing needed for a separate headline addition.
A40: Foreign Slow/Base/High matrices are therefore identical. This is deliberate: exact 2030 exchange totals are the approved floor, ELMED and Piemonte-Savoia are already embedded, and the remaining increments lack the combination of non-embedded status, directional NTC and cutoff-resolving timing needed for a separate headline addition. | B40: Foreign Slow/Base/High matrices are therefore identical. This is deliberate: exact 2030 exchange totals are the approved floor, ELMED and Piemonte-Savoia are already embedded, and the remaining increments lack the combination of non-embedded status, directional NTC and cutoff-resolving timing needed for a separate headline addition. | C40: Foreign Slow/Base/High matrices are therefore identical. This is deliberate: exact 2030 exchange totals are the approved floor, ELMED and Piemonte-Savoia are already embedded, and the remaining increments lack the combination of non-embedded status, directional NTC and cutoff-resolving timing needed for a separate headline addition. | D40: Foreign Slow/Base/High matrices are therefore identical. This is deliberate: exact 2030 exchange totals are the approved floor, ELMED and Piemonte-Savoia are already embedded, and the remaining increments lack the combination of non-embedded status, directional NTC and cutoff-resolving timing needed for a separate headline addition. | E40: Foreign Slow/Base/High matrices are therefore identical. This is deliberate: exact 2030 exchange totals are the approved floor, ELMED and Piemonte-Savoia are already embedded, and the remaining increments lack the combination of non-embedded status, directional NTC and cutoff-resolving timing needed for a separate headline addition. | F40: Foreign Slow/Base/High matrices are therefore identical. This is deliberate: exact 2030 exchange totals are the approved floor, ELMED and Piemonte-Savoia are already embedded, and the remaining increments lack the combination of non-embedded status, directional NTC and cutoff-resolving timing needed for a separate headline addition. | G40: Foreign Slow/Base/High matrices are therefore identical. This is deliberate: exact 2030 exchange totals are the approved floor, ELMED and Piemonte-Savoia are already embedded, and the remaining increments lack the combination of non-embedded status, directional NTC and cutoff-resolving timing needed for a separate headline addition. | H40: Foreign Slow/Base/High matrices are therefore identical. This is deliberate: exact 2030 exchange totals are the approved floor, ELMED and Piemonte-Savoia are already embedded, and the remaining increments lack the combination of non-embedded status, directional NTC and cutoff-resolving timing needed for a separate headline addition. | I40: Foreign Slow/Base/High matrices are therefore identical. This is deliberate: exact 2030 exchange totals are the approved floor, ELMED and Piemonte-Savoia are already embedded, and the remaining increments lack the combination of non-embedded status, directional NTC and cutoff-resolving timing needed for a separate headline addition. | J40: Foreign Slow/Base/High matrices are therefore identical. This is deliberate: exact 2030 exchange totals are the approved floor, ELMED and Piemonte-Savoia are already embedded, and the remaining increments lack the combination of non-embedded status, directional NTC and cutoff-resolving timing needed for a separate headline addition. | K40: Foreign Slow/Base/High matrices are therefore identical. This is deliberate: exact 2030 exchange totals are the approved floor, ELMED and Piemonte-Savoia are already embedded, and the remaining increments lack the combination of non-embedded status, directional NTC and cutoff-resolving timing needed for a separate headline addition. | L40: Foreign Slow/Base/High matrices are therefore identical. This is deliberate: exact 2030 exchange totals are the approved floor, ELMED and Piemonte-Savoia are already embedded, and the remaining increments lack the combination of non-embedded status, directional NTC and cutoff-resolving timing needed for a separate headline addition. | M40: Foreign Slow/Base/High matrices are therefore identical. This is deliberate: exact 2030 exchange totals are the approved floor, ELMED and Piemonte-Savoia are already embedded, and the remaining increments lack the combination of non-embedded status, directional NTC and cutoff-resolving timing needed for a separate headline addition. | N40: Foreign Slow/Base/High matrices are therefore identical. This is deliberate: exact 2030 exchange totals are the approved floor, ELMED and Piemonte-Savoia are already embedded, and the remaining increments lack the combination of non-embedded status, directional NTC and cutoff-resolving timing needed for a separate headline addition. | O40: Foreign Slow/Base/High matrices are therefore identical. This is deliberate: exact 2030 exchange totals are the approved floor, ELMED and Piemonte-Savoia are already embedded, and the remaining increments lack the combination of non-embedded status, directional NTC and cutoff-resolving timing needed for a separate headline addition. | P40: Foreign Slow/Base/High matrices are therefore identical. This is deliberate: exact 2030 exchange totals are the approved floor, ELMED and Piemonte-Savoia are already embedded, and the remaining increments lack the combination of non-embedded status, directional NTC and cutoff-resolving timing needed for a separate headline addition. | Q40: Foreign Slow/Base/High matrices are therefore identical. This is deliberate: exact 2030 exchange totals are the approved floor, ELMED and Piemonte-Savoia are already embedded, and the remaining increments lack the combination of non-embedded status, directional NTC and cutoff-resolving timing needed for a separate headline addition.
A41: Foreign Slow/Base/High matrices are therefore identical. This is deliberate: exact 2030 exchange totals are the approved floor, ELMED and Piemonte-Savoia are already embedded, and the remaining increments lack the combination of non-embedded status, directional NTC and cutoff-resolving timing needed for a separate headline addition. | B41: Foreign Slow/Base/High matrices are therefore identical. This is deliberate: exact 2030 exchange totals are the approved floor, ELMED and Piemonte-Savoia are already embedded, and the remaining increments lack the combination of non-embedded status, directional NTC and cutoff-resolving timing needed for a separate headline addition. | C41: Foreign Slow/Base/High matrices are therefore identical. This is deliberate: exact 2030 exchange totals are the approved floor, ELMED and Piemonte-Savoia are already embedded, and the remaining increments lack the combination of non-embedded status, directional NTC and cutoff-resolving timing needed for a separate headline addition. | D41: Foreign Slow/Base/High matrices are therefore identical. This is deliberate: exact 2030 exchange totals are the approved floor, ELMED and Piemonte-Savoia are already embedded, and the remaining increments lack the combination of non-embedded status, directional NTC and cutoff-resolving timing needed for a separate headline addition. | E41: Foreign Slow/Base/High matrices are therefore identical. This is deliberate: exact 2030 exchange totals are the approved floor, ELMED and Piemonte-Savoia are already embedded, and the remaining increments lack the combination of non-embedded status, directional NTC and cutoff-resolving timing needed for a separate headline addition. | F41: Foreign Slow/Base/High matrices are therefore identical. This is deliberate: exact 2030 exchange totals are the approved floor, ELMED and Piemonte-Savoia are already embedded, and the remaining increments lack the combination of non-embedded status, directional NTC and cutoff-resolving timing needed for a separate headline addition. | G41: Foreign Slow/Base/High matrices are therefore identical. This is deliberate: exact 2030 exchange totals are the approved floor, ELMED and Piemonte-Savoia are already embedded, and the remaining increments lack the combination of non-embedded status, directional NTC and cutoff-resolving timing needed for a separate headline addition. | H41: Foreign Slow/Base/High matrices are therefore identical. This is deliberate: exact 2030 exchange totals are the approved floor, ELMED and Piemonte-Savoia are already embedded, and the remaining increments lack the combination of non-embedded status, directional NTC and cutoff-resolving timing needed for a separate headline addition. | I41: Foreign Slow/Base/High matrices are therefore identical. This is deliberate: exact 2030 exchange totals are the approved floor, ELMED and Piemonte-Savoia are already embedded, and the remaining increments lack the combination of non-embedded status, directional NTC and cutoff-resolving timing needed for a separate headline addition. | J41: Foreign Slow/Base/High matrices are therefore identical. This is deliberate: exact 2030 exchange totals are the approved floor, ELMED and Piemonte-Savoia are already embedded, and the remaining increments lack the combination of non-embedded status, directional NTC and cutoff-resolving timing needed for a separate headline addition. | K41: Foreign Slow/Base/High matrices are therefore identical. This is deliberate: exact 2030 exchange totals are the approved floor, ELMED and Piemonte-Savoia are already embedded, and the remaining increments lack the combination of non-embedded status, directional NTC and cutoff-resolving timing needed for a separate headline addition. | L41: Foreign Slow/Base/High matrices are therefore identical. This is deliberate: exact 2030 exchange totals are the approved floor, ELMED and Piemonte-Savoia are already embedded, and the remaining increments lack the combination of non-embedded status, directional NTC and cutoff-resolving timing needed for a separate headline addition. | M41: Foreign Slow/Base/High matrices are therefore identical. This is deliberate: exact 2030 exchange totals are the approved floor, ELMED and Piemonte-Savoia are already embedded, and the remaining increments lack the combination of non-embedded status, directional NTC and cutoff-resolving timing needed for a separate headline addition. | N41: Foreign Slow/Base/High matrices are therefore identical. This is deliberate: exact 2030 exchange totals are the approved floor, ELMED and Piemonte-Savoia are already embedded, and the remaining increments lack the combination of non-embedded status, directional NTC and cutoff-resolving timing needed for a separate headline addition. | O41: Foreign Slow/Base/High matrices are therefore identical. This is deliberate: exact 2030 exchange totals are the approved floor, ELMED and Piemonte-Savoia are already embedded, and the remaining increments lack the combination of non-embedded status, directional NTC and cutoff-resolving timing needed for a separate headline addition. | P41: Foreign Slow/Base/High matrices are therefore identical. This is deliberate: exact 2030 exchange totals are the approved floor, ELMED and Piemonte-Savoia are already embedded, and the remaining increments lack the combination of non-embedded status, directional NTC and cutoff-resolving timing needed for a separate headline addition. | Q41: Foreign Slow/Base/High matrices are therefore identical. This is deliberate: exact 2030 exchange totals are the approved floor, ELMED and Piemonte-Savoia are already embedded, and the remaining increments lack the combination of non-embedded status, directional NTC and cutoff-resolving timing needed for a separate headline addition.

Sheet 09_TECH_COSTS
A1: Parametri tecnici, costi marginali e availability termoelettrica
A2: Unifica parametri tecnologici, fuel/CO₂ e availability che prima erano distribuiti su più fogli.
A4: Parametri tecnologici principali
A5: Parameter | B5: 2040 Base | C5: 2050 Base | D5: Unit | E5: Source / note
A6: CCGT efficiency | B6: 0.59 | C6: 0.6 | D6: p.u. | E6: technology-data candidate / CLI pin prevails
A7: CCGT VOM | B7: 5.4768 | C7: 5.3432 | D7: EUR/MWh_e | E7: technology-data candidate
A8: OCGT efficiency | B8: 0.42 | C8: 0.43 | D8: p.u. | E8: technology-data candidate
A9: OCGT VOM | B9: 6.0111 | C9: 6.0111 | D9: EUR/MWh_e | E9: technology-data candidate
A10: Gas CO₂ intensity | B10: 0.198 | C10: 0.198 | D10: tCO₂/MWh_th | E10: technology-data
A11: Battery one-way efficiency | B11: 0.9486833 | C11: 0.9486833 | D11: p.u. | E11: round-trip 90%
A12: PHS one-way efficiency | B12: 0.8660254 | C12: 0.8660254 | D12: p.u. | E12: round-trip 75%
A13: Nuclear efficiency | C13: 0.36 | D13: p.u. | E13: 2050 nuclear branch
A14: Nuclear VOM | C14: 4.459 | D14: EUR/MWh_e | E14: 2050 nuclear branch
A15: Nuclear fuel | C15: 7.4536 | D15: EUR/MWh_th | E15: 2050 nuclear branch
A18: Fuel + CO₂ + marginal cost
A19: Year | B19: Technology | C19: Gas EUR2025/MWh_th | D19: CO₂ EUR2025/t | E19: Efficiency | F19: VOM | G19: Fuel component | H19: CO₂ component | I19: Final marginal cost | J19: Source
A20: 2040 | B20: CCGT | C20: 38.056346 | D20: 104.5504 | E20: 0.59 | F20: 5.4768 | G20: 64.502281 | H20: 35.086405 | I20: 105.06549 | J20: S01 / S09 | S01 / S09 | EXT-TD
A21: 2040 | B21: OCGT | C21: 38.056346 | D21: 104.5504 | E21: 0.42 | F21: 6.0111 | G21: 90.610347 | H21: 49.288046 | I21: 145.90949 | J21: S01 / S09 | S01 / S09 | EXT-TD
A22: 2050 | B22: CCGT | C22: 22.7578 | D22: 400 | E22: 0.6 | F22: 5.3432 | G22: 37.929667 | H22: 132 | I22: 175.27287 | J22: S33 / S35 / D5-005
A23: 2050 | B23: OCGT | C23: 22.7578 | D23: 400 | E23: 0.43 | F23: 6.0111 | G23: 52.925116 | H23: 184.18605 | I23: 243.12226 | J23: S33 / S35 / D5-005
A27: CO₂ 2050 — overlay di sensitivity
A28: Case | B28: EUR2025/tCO₂ | C28: Anchor | D28: Use
A29: LOW | B29: 175 | C29: TYNDP / APS | D29: Sensitivity
A30: BASE | B30: 400 | C30: VIIEW EU ETS | D30: Base 2050
A31: HIGH | B31: 550 | C31: VIIEW partial removals | D31: Sensitivity
A32: EXTREME | B32: 1000 | C32: VIIEW weak/no removals | D32: Stress only
A35: Availability termoelettrica per zona
A36: Zone | B36: Operational derating | C36: p_max_pu outside maintenance | D36: CCGT planned maintenance | E36: OCGT planned maintenance | F36: Traditional thermal | G36: Rule
A37: NORD | B37: 0.22 | C37: 0.78 | D37: CCGT 1.353 h | E37: OCGT 857 h | F37: Traditional 1.344 h | G37: No extra forced-outage multiplier
A38: CNOR | B38: 0.31 | C38: 0.69 | D38: CCGT 1.353 h | E38: OCGT 857 h | F38: Traditional 1.344 h | G38: No extra forced-outage multiplier
A39: CSUD | B39: 0.24 | C39: 0.76 | D39: CCGT 1.353 h | E39: OCGT 857 h | F39: Traditional 1.344 h | G39: No extra forced-outage multiplier
A40: SUD | B40: 0.23 | C40: 0.77 | D40: CCGT 1.353 h | E40: OCGT 857 h | F40: Traditional 1.344 h | G40: No extra forced-outage multiplier
A41: CALA | B41: 0.17 | C41: 0.83 | D41: CCGT 1.353 h | E41: OCGT 857 h | F41: Traditional 1.344 h | G41: No extra forced-outage multiplier
A42: SICI | B42: 0.25 | C42: 0.75 | D42: CCGT 1.353 h | E42: OCGT 857 h | F42: Traditional 1.344 h | G42: No extra forced-outage multiplier
A43: SARD | B43: 0.26 | C43: 0.74 | D43: CCGT 1.353 h | E43: OCGT 857 h | F43: Traditional 1.344 h | G43: No extra forced-outage multiplier
A46: Model boundary: filter long-duration unavailable units from p_nom; represent scheduled maintenance separately; apply zonal operational/environmental derating outside maintenance. For an aggregated zonal network, the annual-equivalent factor is a fallback. Do not add a second forced-outage multiplier.

Sheet 10_NUCLEAR
A1: Nuclear assumptions — headline cases and secondary availability overlays | B1: Nuclear assumptions — headline cases and secondary availability overlays | C1: Nuclear assumptions — headline cases and secondary availability overlays | D1: Nuclear assumptions — headline cases and secondary availability overlays | E1: Nuclear assumptions — headline cases and secondary availability overlays | F1: Nuclear assumptions — headline cases and secondary availability overlays | G1: Nuclear assumptions — headline cases and secondary availability overlays | H1: Nuclear assumptions — headline cases and secondary availability overlays | I1: Nuclear assumptions — headline cases and secondary availability overlays | J1: Nuclear assumptions — headline cases and secondary availability overlays
A2: All three 2050 headline physical scenarios retain the PNIEC 8 GW branch. Nuclear capacity is not multiplied with FER and High does not raise nuclear availability; availability sensitivities remain overlays. | B2: All three 2050 headline physical scenarios retain the PNIEC 8 GW branch. Nuclear capacity is not multiplied with FER and High does not raise nuclear availability; availability sensitivities remain overlays. | C2: All three 2050 headline physical scenarios retain the PNIEC 8 GW branch. Nuclear capacity is not multiplied with FER and High does not raise nuclear availability; availability sensitivities remain overlays. | D2: All three 2050 headline physical scenarios retain the PNIEC 8 GW branch. Nuclear capacity is not multiplied with FER and High does not raise nuclear availability; availability sensitivities remain overlays. | E2: All three 2050 headline physical scenarios retain the PNIEC 8 GW branch. Nuclear capacity is not multiplied with FER and High does not raise nuclear availability; availability sensitivities remain overlays. | F2: All three 2050 headline physical scenarios retain the PNIEC 8 GW branch. Nuclear capacity is not multiplied with FER and High does not raise nuclear availability; availability sensitivities remain overlays. | G2: All three 2050 headline physical scenarios retain the PNIEC 8 GW branch. Nuclear capacity is not multiplied with FER and High does not raise nuclear availability; availability sensitivities remain overlays. | H2: All three 2050 headline physical scenarios retain the PNIEC 8 GW branch. Nuclear capacity is not multiplied with FER and High does not raise nuclear availability; availability sensitivities remain overlays. | I2: All three 2050 headline physical scenarios retain the PNIEC 8 GW branch. Nuclear capacity is not multiplied with FER and High does not raise nuclear availability; availability sensitivities remain overlays. | J2: All three 2050 headline physical scenarios retain the PNIEC 8 GW branch. Nuclear capacity is not multiplied with FER and High does not raise nuclear availability; availability sensitivities remain overlays.
A4: Scenario ID | B4: Horizon | C4: Nuclear GW | D4: NORD GW | E4: CSUD GW | F4: Availability | G4: Annual ceiling TWh | H4: PNIEC generation QA TWh | I4: Class | J4: Treatment
A5: IT2040_SLOW | B5: 2040 | C5: =D5+E5 -> 0 | D5: 0 | E5: 0 | F5: 0 | G5: =C5*8760*F5/1000 -> 0 | I5: Not applicable | J5: No nuclear
A6: IT2040_BASE | B6: 2040 | C6: =D6+E6 -> 0 | D6: 0 | E6: 0 | F6: 0 | G6: =C6*8760*F6/1000 -> 0 | I6: Not applicable | J6: No nuclear
A7: IT2040_HIGH | B7: 2040 | C7: =D7+E7 -> 0 | D7: 0 | E7: 0 | F7: 0 | G7: =C7*8760*F7/1000 -> 0 | I7: Not applicable | J7: No nuclear
A8: IT2050_SLOW | B8: 2050 | C8: =D8+E8 -> 8 | D8: 5 | E8: 3 | F8: 0.9245 | G8: =C8*8760*F8/1000 -> 64.78896 | I8: Direct national + approved allocation | J8: Fixed 8 GW headline branch
A9: IT2050_BASE | B9: 2050 | C9: =D9+E9 -> 8 | D9: 5 | E9: 3 | F9: 0.9245 | G9: =C9*8760*F9/1000 -> 64.78896 | H9: 64.2 | I9: Direct national + approved allocation | J9: Fixed 8 GW headline branch
A10: IT2050_HIGH | B10: 2050 | C10: =D10+E10 -> 8 | D10: 5 | E10: 3 | F10: 0.9245 | G10: =C10*8760*F10/1000 -> 64.78896 | I10: Direct national + approved allocation | J10: Fixed 8 GW headline branch
A13: Availability overlays — independent of headline physical scenario (same as other theraml technologies, availability does not change across scnearios) | B13: Availability overlays — independent of headline physical scenario | C13: Availability overlays — independent of headline physical scenario | D13: Availability overlays — independent of headline physical scenario | E13: Availability overlays — independent of headline physical scenario | F13: Availability overlays — independent of headline physical scenario | G13: Availability overlays — independent of headline physical scenario | H13: Availability overlays — independent of headline physical scenario | I13: Availability overlays — independent of headline physical scenario | J13: Availability overlays — independent of headline physical scenario
A14: Overlay | B14: Availability | C14: 8 GW ceiling TWh | D14: Use
A15: LOW-NORMAL | B15: 0.9245 | C15: =8*8760*B15/1000 -> 64.78896 | D15: Headline default
A16: BASE | B16: 0.9245 | C16: =8*8760*B16/1000 -> 64.78896 | D16: Headline default
A17: HIGH | B17: 0.9245 | C17: =8*8760*B17/1000 -> 64.78896 | D17: Headline default
A20: The PNIEC 64.2 TWh value is a Base annual-generation control. It is not imposed on Slow or High; dispatch is endogenous. The 5 GW NORD / 3 GW CSUD siting is an approved project allocation, not a source-published zonal split. | B20: The PNIEC 64.2 TWh value is a Base annual-generation control. It is not imposed on Slow or High; dispatch is endogenous. The 5 GW NORD / 3 GW CSUD siting is an approved project allocation, not a source-published zonal split. | C20: The PNIEC 64.2 TWh value is a Base annual-generation control. It is not imposed on Slow or High; dispatch is endogenous. The 5 GW NORD / 3 GW CSUD siting is an approved project allocation, not a source-published zonal split. | D20: The PNIEC 64.2 TWh value is a Base annual-generation control. It is not imposed on Slow or High; dispatch is endogenous. The 5 GW NORD / 3 GW CSUD siting is an approved project allocation, not a source-published zonal split. | E20: The PNIEC 64.2 TWh value is a Base annual-generation control. It is not imposed on Slow or High; dispatch is endogenous. The 5 GW NORD / 3 GW CSUD siting is an approved project allocation, not a source-published zonal split. | F20: The PNIEC 64.2 TWh value is a Base annual-generation control. It is not imposed on Slow or High; dispatch is endogenous. The 5 GW NORD / 3 GW CSUD siting is an approved project allocation, not a source-published zonal split. | G20: The PNIEC 64.2 TWh value is a Base annual-generation control. It is not imposed on Slow or High; dispatch is endogenous. The 5 GW NORD / 3 GW CSUD siting is an approved project allocation, not a source-published zonal split. | H20: The PNIEC 64.2 TWh value is a Base annual-generation control. It is not imposed on Slow or High; dispatch is endogenous. The 5 GW NORD / 3 GW CSUD siting is an approved project allocation, not a source-published zonal split. | I20: The PNIEC 64.2 TWh value is a Base annual-generation control. It is not imposed on Slow or High; dispatch is endogenous. The 5 GW NORD / 3 GW CSUD siting is an approved project allocation, not a source-published zonal split. | J20: The PNIEC 64.2 TWh value is a Base annual-generation control. It is not imposed on Slow or High; dispatch is endogenous. The 5 GW NORD / 3 GW CSUD siting is an approved project allocation, not a source-published zonal split.
A21: The PNIEC 64.2 TWh value is a Base annual-generation control. It is not imposed on Slow or High; dispatch is endogenous. The 5 GW NORD / 3 GW CSUD siting is an approved project allocation, not a source-published zonal split. | B21: The PNIEC 64.2 TWh value is a Base annual-generation control. It is not imposed on Slow or High; dispatch is endogenous. The 5 GW NORD / 3 GW CSUD siting is an approved project allocation, not a source-published zonal split. | C21: The PNIEC 64.2 TWh value is a Base annual-generation control. It is not imposed on Slow or High; dispatch is endogenous. The 5 GW NORD / 3 GW CSUD siting is an approved project allocation, not a source-published zonal split. | D21: The PNIEC 64.2 TWh value is a Base annual-generation control. It is not imposed on Slow or High; dispatch is endogenous. The 5 GW NORD / 3 GW CSUD siting is an approved project allocation, not a source-published zonal split. | E21: The PNIEC 64.2 TWh value is a Base annual-generation control. It is not imposed on Slow or High; dispatch is endogenous. The 5 GW NORD / 3 GW CSUD siting is an approved project allocation, not a source-published zonal split. | F21: The PNIEC 64.2 TWh value is a Base annual-generation control. It is not imposed on Slow or High; dispatch is endogenous. The 5 GW NORD / 3 GW CSUD siting is an approved project allocation, not a source-published zonal split. | G21: The PNIEC 64.2 TWh value is a Base annual-generation control. It is not imposed on Slow or High; dispatch is endogenous. The 5 GW NORD / 3 GW CSUD siting is an approved project allocation, not a source-published zonal split. | H21: The PNIEC 64.2 TWh value is a Base annual-generation control. It is not imposed on Slow or High; dispatch is endogenous. The 5 GW NORD / 3 GW CSUD siting is an approved project allocation, not a source-published zonal split. | I21: The PNIEC 64.2 TWh value is a Base annual-generation control. It is not imposed on Slow or High; dispatch is endogenous. The 5 GW NORD / 3 GW CSUD siting is an approved project allocation, not a source-published zonal split. | J21: The PNIEC 64.2 TWh value is a Base annual-generation control. It is not imposed on Slow or High; dispatch is endogenous. The 5 GW NORD / 3 GW CSUD siting is an approved project allocation, not a source-published zonal split.
A22: The PNIEC 64.2 TWh value is a Base annual-generation control. It is not imposed on Slow or High; dispatch is endogenous. The 5 GW NORD / 3 GW CSUD siting is an approved project allocation, not a source-published zonal split. | B22: The PNIEC 64.2 TWh value is a Base annual-generation control. It is not imposed on Slow or High; dispatch is endogenous. The 5 GW NORD / 3 GW CSUD siting is an approved project allocation, not a source-published zonal split. | C22: The PNIEC 64.2 TWh value is a Base annual-generation control. It is not imposed on Slow or High; dispatch is endogenous. The 5 GW NORD / 3 GW CSUD siting is an approved project allocation, not a source-published zonal split. | D22: The PNIEC 64.2 TWh value is a Base annual-generation control. It is not imposed on Slow or High; dispatch is endogenous. The 5 GW NORD / 3 GW CSUD siting is an approved project allocation, not a source-published zonal split. | E22: The PNIEC 64.2 TWh value is a Base annual-generation control. It is not imposed on Slow or High; dispatch is endogenous. The 5 GW NORD / 3 GW CSUD siting is an approved project allocation, not a source-published zonal split. | F22: The PNIEC 64.2 TWh value is a Base annual-generation control. It is not imposed on Slow or High; dispatch is endogenous. The 5 GW NORD / 3 GW CSUD siting is an approved project allocation, not a source-published zonal split. | G22: The PNIEC 64.2 TWh value is a Base annual-generation control. It is not imposed on Slow or High; dispatch is endogenous. The 5 GW NORD / 3 GW CSUD siting is an approved project allocation, not a source-published zonal split. | H22: The PNIEC 64.2 TWh value is a Base annual-generation control. It is not imposed on Slow or High; dispatch is endogenous. The 5 GW NORD / 3 GW CSUD siting is an approved project allocation, not a source-published zonal split. | I22: The PNIEC 64.2 TWh value is a Base annual-generation control. It is not imposed on Slow or High; dispatch is endogenous. The 5 GW NORD / 3 GW CSUD siting is an approved project allocation, not a source-published zonal split. | J22: The PNIEC 64.2 TWh value is a Base annual-generation control. It is not imposed on Slow or High; dispatch is endogenous. The 5 GW NORD / 3 GW CSUD siting is an approved project allocation, not a source-published zonal split.

Sheet 11_PYPSA_IMPLEMENTATION
A1: PyPSA-Eur implementation map — v2.8 | B1: PyPSA-Eur implementation map — v2.8 | C1: PyPSA-Eur implementation map — v2.8 | D1: PyPSA-Eur implementation map — v2.8 | E1: PyPSA-Eur implementation map — v2.8 | F1: PyPSA-Eur implementation map — v2.8 | G1: PyPSA-Eur implementation map — v2.8 | H1: PyPSA-Eur implementation map — v2.8 | I1: PyPSA-Eur implementation map — v2.8 | J1: PyPSA-Eur implementation map — v2.8 | K1: PyPSA-Eur implementation map — v2.8 | L1: PyPSA-Eur implementation map — v2.8
A2: Workbook formulas define scenario inputs; the high-voltage model does not receive invented distribution-flexibility or transmission MW. | B2: Workbook formulas define scenario inputs; the high-voltage model does not receive invented distribution-flexibility or transmission MW. | C2: Workbook formulas define scenario inputs; the high-voltage model does not receive invented distribution-flexibility or transmission MW. | D2: Workbook formulas define scenario inputs; the high-voltage model does not receive invented distribution-flexibility or transmission MW. | E2: Workbook formulas define scenario inputs; the high-voltage model does not receive invented distribution-flexibility or transmission MW. | F2: Workbook formulas define scenario inputs; the high-voltage model does not receive invented distribution-flexibility or transmission MW. | G2: Workbook formulas define scenario inputs; the high-voltage model does not receive invented distribution-flexibility or transmission MW. | H2: Workbook formulas define scenario inputs; the high-voltage model does not receive invented distribution-flexibility or transmission MW. | I2: Workbook formulas define scenario inputs; the high-voltage model does not receive invented distribution-flexibility or transmission MW. | J2: Workbook formulas define scenario inputs; the high-voltage model does not receive invented distribution-flexibility or transmission MW. | K2: Workbook formulas define scenario inputs; the high-voltage model does not receive invented distribution-flexibility or transmission MW. | L2: Workbook formulas define scenario inputs; the high-voltage model does not receive invented distribution-flexibility or transmission MW.
A4: Component | B4: Workbook source | C4: PyPSA object | D4: Field | E4: Base | F4: Slow | G4: High | H4: Formula / method | I4: Evidence class | J4: User-decision flag | K4: QA | L4: Boundary / note
A5: Scenario IDs | B5: 02_SCENARIOS A5:A10 | C5: Run config | D5: scenario | E5: Exact IDs | F5: Exact IDs | G5: Exact IDs | H5: Read six rows only | I5: Project governance | J5: No | K5: Count=6 | L5: Benchmarks/overlays loaded separately
A6: Annual total demand | B6: 06_DEMAND_BY_ZONE | C6: Load | D6: p_set annual target | E6: Base | F6: Base | G6: Base x1.10 | H6: Sum hourly profile then scale to zonal annual target | I6: Direct national / fixed user share | J6: No | K6: Zone sum=national | L6: Source total includes losses; do not add a second loss load
A7: Rigid demand | B7: 06_DEMAND_BY_ZONE | C7: Load | D7: p_set | E7: Base | F7: Base | G7: Base x1.10 | H7: Same frozen share in every zone | I7: Reconciled/direct | J7: No | K7: Rigid+P2X=total | L7: 2040 411.5 is total less direct 27.5 P2X
A8: Power-to-X | B8: 06_DEMAND_BY_ZONE | C8: Link/Load | D8: p_set / flexible bounds | E8: Base | F8: Base | G8: Base x1.10 | H8: Same frozen share; no separate P2X geography | I8: Direct national / fixed user share | J8: No | K8: Zone sum=national | L8: Operational flexibility remains modelled separately from annual allocation
A9: Solar rooftop | B9: 04_GENERATION_BY_ZONE | C9: Generator | D9: p_nom | E9: Base | F9: Base x0.80 | G9: Base x1.10 | H9: Formula by zone | I9: Direct national / inherited zonal proxy | J9: Yes | K9: National reconciliation | L9: Distributed proxy retained from v2.7
A10: Solar utility | B10: 04_GENERATION_BY_ZONE | C10: Generator | D10: p_nom | E10: Base | F10: Base x0.80 | G10: Base x1.10 | H10: Formula by zone | I10: Direct national / inherited zonal proxy | J10: Yes | K10: National reconciliation
A11: Onshore wind | B11: 04_GENERATION_BY_ZONE | C11: Generator | D11: p_nom | E11: Base | F11: Base x0.80 | G11: Base x1.10 | H11: Formula by zone | I11: Direct national / inherited zonal proxy | J11: Yes | K11: National reconciliation
A12: Offshore wind | B12: 04_GENERATION_BY_ZONE | C12: Generator | D12: p_nom | E12: Base | F12: Base x0.80 | G12: Base x1.10 | H12: Formula by zone | I12: Direct national / inherited zonal proxy | J12: Yes | K12: National reconciliation
A13: Nuclear | B13: 10_NUCLEAR | C13: Generator | D13: p_nom | E13: 0/8 GW | F13: Same | G13: Same | H13: 5 GW NORD + 3 GW CSUD in 2050 | I13: Direct national + approved allocation | J13: Approved | K13: 2050 sum=8 | L13: Availability overlays separate
A14: Thermal 2040 | B14: 04_GENERATION_BY_ZONE / evidence CSV | C14: Generator portfolio | D14: sum p_nom | E14: 55 GW | F14: 55 GW | G14: 55 GW | H14: Filter/map eligible plant/cohort records and reconcile to envelope | I14: Direct approximate national | J14: Project plant mapping | K14: sum p_nom=55 | L14: No published CCGT/OCGT or zonal target split
A15: Programmable 2050 | B15: 04_GENERATION_BY_ZONE / evidence CSV | C15: Generator portfolio | D15: adequacy control | E15: >=30 GW | F15: >=30 GW | G15: >=30 GW | H15: Use as approximate all-programmable floor; do not interpret as gas | I15: Derived approximate | J15: Project plant mapping | K15: control only | L15: 22.7 TWh is Base non-nuclear generation QA, not MW
A16: Hydrogen turbines | B16: Evidence CSV | C16: Generator | D16: p_nom | E16: Absent | F16: Absent | G16: Absent | H16: Create only from explicit project/plant data | I16: Absent | J16: Yes if later added | K16: No inferred MW | L16: Hydrogen demand/P2G2P narrative is insufficient
A17: Battery power | B17: 05_STORAGE_BY_ZONE | C17: StorageUnit/Store+Links | D17: p_nom charge/discharge | E17: Base | F17: Base x0.80 | G17: Base x1.10 | H17: Symmetric charge/discharge in this workbook | I17: Direct/derived portfolio | J17: No | K17: Zone sum=national
A18: Battery energy | B18: 05_STORAGE_BY_ZONE | C18: Store | D18: e_nom | E18: Base | F18: Base x0.80 | G18: Base x1.10 | H18: Formula by class/zone | I18: Direct/derived portfolio | J18: No | K18: duration unchanged | L18: MACSE subset not summed
A19: Internal links | B19: 07_INTERZONAL_BY_ZONE | C19: Link | D19: p_nom direction | E19: PdS 2040 | F19: Base less delayed late projects | G19: Exactly Base | H19: Explicit directional links | I19: Direct Base / derived Slow | J19: No | K19: High=Base; Slow2050=Slow2040 | L19: Preserve asymmetry
A20: Foreign borders | B20: 08_FOREIGN_BY_ZONE | C20: External PyPSA system / optional Link | D20: endogenous or manual NTC | E20: 2030 floor | F20: Same | G20: Same | H20: Do not add planned increment already embedded | I20: Direct QA totals | J20: Yes for manual NTC | K20: All headline matrices equal | L20: Endogenous PyPSA-Eur is default
A21: High distribution flexibility | B21: 02_SCENARIOS | C21: Outside explicit HV model | D21: n/a | E21: n/a | F21: n/a | G21: Implicit | H21: Narrative assumption only | I21: Assumption / limitation | J21: No HV encoding | K21: No added link MW | L21: TIDE/UVAN/UVAZ, EDGE, RomeFlex, MiNDFlex and local DSO flexibility are contextual support
A25: Implementation order: load fixed zonal demand shares -> select scenario row -> apply FER/BESS formulas -> load the scenario-specific directional network -> map plant/cohort dispatchable assets to national controls -> run dispatch and annual QA. Distribution-level High flexibility remains an implicit limitation, not a hidden HV parameter. | B25: Implementation order: load fixed zonal demand shares -> select scenario row -> apply FER/BESS formulas -> load the scenario-specific directional network -> map plant/cohort dispatchable assets to national controls -> run dispatch and annual QA. Distribution-level High flexibility remains an implicit limitation, not a hidden HV parameter. | C25: Implementation order: load fixed zonal demand shares -> select scenario row -> apply FER/BESS formulas -> load the scenario-specific directional network -> map plant/cohort dispatchable assets to national controls -> run dispatch and annual QA. Distribution-level High flexibility remains an implicit limitation, not a hidden HV parameter. | D25: Implementation order: load fixed zonal demand shares -> select scenario row -> apply FER/BESS formulas -> load the scenario-specific directional network -> map plant/cohort dispatchable assets to national controls -> run dispatch and annual QA. Distribution-level High flexibility remains an implicit limitation, not a hidden HV parameter. | E25: Implementation order: load fixed zonal demand shares -> select scenario row -> apply FER/BESS formulas -> load the scenario-specific directional network -> map plant/cohort dispatchable assets to national controls -> run dispatch and annual QA. Distribution-level High flexibility remains an implicit limitation, not a hidden HV parameter. | F25: Implementation order: load fixed zonal demand shares -> select scenario row -> apply FER/BESS formulas -> load the scenario-specific directional network -> map plant/cohort dispatchable assets to national controls -> run dispatch and annual QA. Distribution-level High flexibility remains an implicit limitation, not a hidden HV parameter. | G25: Implementation order: load fixed zonal demand shares -> select scenario row -> apply FER/BESS formulas -> load the scenario-specific directional network -> map plant/cohort dispatchable assets to national controls -> run dispatch and annual QA. Distribution-level High flexibility remains an implicit limitation, not a hidden HV parameter. | H25: Implementation order: load fixed zonal demand shares -> select scenario row -> apply FER/BESS formulas -> load the scenario-specific directional network -> map plant/cohort dispatchable assets to national controls -> run dispatch and annual QA. Distribution-level High flexibility remains an implicit limitation, not a hidden HV parameter. | I25: Implementation order: load fixed zonal demand shares -> select scenario row -> apply FER/BESS formulas -> load the scenario-specific directional network -> map plant/cohort dispatchable assets to national controls -> run dispatch and annual QA. Distribution-level High flexibility remains an implicit limitation, not a hidden HV parameter. | J25: Implementation order: load fixed zonal demand shares -> select scenario row -> apply FER/BESS formulas -> load the scenario-specific directional network -> map plant/cohort dispatchable assets to national controls -> run dispatch and annual QA. Distribution-level High flexibility remains an implicit limitation, not a hidden HV parameter. | K25: Implementation order: load fixed zonal demand shares -> select scenario row -> apply FER/BESS formulas -> load the scenario-specific directional network -> map plant/cohort dispatchable assets to national controls -> run dispatch and annual QA. Distribution-level High flexibility remains an implicit limitation, not a hidden HV parameter. | L25: Implementation order: load fixed zonal demand shares -> select scenario row -> apply FER/BESS formulas -> load the scenario-specific directional network -> map plant/cohort dispatchable assets to national controls -> run dispatch and annual QA. Distribution-level High flexibility remains an implicit limitation, not a hidden HV parameter.
A26: Implementation order: load fixed zonal demand shares -> select scenario row -> apply FER/BESS formulas -> load the scenario-specific directional network -> map plant/cohort dispatchable assets to national controls -> run dispatch and annual QA. Distribution-level High flexibility remains an implicit limitation, not a hidden HV parameter. | B26: Implementation order: load fixed zonal demand shares -> select scenario row -> apply FER/BESS formulas -> load the scenario-specific directional network -> map plant/cohort dispatchable assets to national controls -> run dispatch and annual QA. Distribution-level High flexibility remains an implicit limitation, not a hidden HV parameter. | C26: Implementation order: load fixed zonal demand shares -> select scenario row -> apply FER/BESS formulas -> load the scenario-specific directional network -> map plant/cohort dispatchable assets to national controls -> run dispatch and annual QA. Distribution-level High flexibility remains an implicit limitation, not a hidden HV parameter. | D26: Implementation order: load fixed zonal demand shares -> select scenario row -> apply FER/BESS formulas -> load the scenario-specific directional network -> map plant/cohort dispatchable assets to national controls -> run dispatch and annual QA. Distribution-level High flexibility remains an implicit limitation, not a hidden HV parameter. | E26: Implementation order: load fixed zonal demand shares -> select scenario row -> apply FER/BESS formulas -> load the scenario-specific directional network -> map plant/cohort dispatchable assets to national controls -> run dispatch and annual QA. Distribution-level High flexibility remains an implicit limitation, not a hidden HV parameter. | F26: Implementation order: load fixed zonal demand shares -> select scenario row -> apply FER/BESS formulas -> load the scenario-specific directional network -> map plant/cohort dispatchable assets to national controls -> run dispatch and annual QA. Distribution-level High flexibility remains an implicit limitation, not a hidden HV parameter. | G26: Implementation order: load fixed zonal demand shares -> select scenario row -> apply FER/BESS formulas -> load the scenario-specific directional network -> map plant/cohort dispatchable assets to national controls -> run dispatch and annual QA. Distribution-level High flexibility remains an implicit limitation, not a hidden HV parameter. | H26: Implementation order: load fixed zonal demand shares -> select scenario row -> apply FER/BESS formulas -> load the scenario-specific directional network -> map plant/cohort dispatchable assets to national controls -> run dispatch and annual QA. Distribution-level High flexibility remains an implicit limitation, not a hidden HV parameter. | I26: Implementation order: load fixed zonal demand shares -> select scenario row -> apply FER/BESS formulas -> load the scenario-specific directional network -> map plant/cohort dispatchable assets to national controls -> run dispatch and annual QA. Distribution-level High flexibility remains an implicit limitation, not a hidden HV parameter. | J26: Implementation order: load fixed zonal demand shares -> select scenario row -> apply FER/BESS formulas -> load the scenario-specific directional network -> map plant/cohort dispatchable assets to national controls -> run dispatch and annual QA. Distribution-level High flexibility remains an implicit limitation, not a hidden HV parameter. | K26: Implementation order: load fixed zonal demand shares -> select scenario row -> apply FER/BESS formulas -> load the scenario-specific directional network -> map plant/cohort dispatchable assets to national controls -> run dispatch and annual QA. Distribution-level High flexibility remains an implicit limitation, not a hidden HV parameter. | L26: Implementation order: load fixed zonal demand shares -> select scenario row -> apply FER/BESS formulas -> load the scenario-specific directional network -> map plant/cohort dispatchable assets to national controls -> run dispatch and annual QA. Distribution-level High flexibility remains an implicit limitation, not a hidden HV parameter.
A27: Implementation order: load fixed zonal demand shares -> select scenario row -> apply FER/BESS formulas -> load the scenario-specific directional network -> map plant/cohort dispatchable assets to national controls -> run dispatch and annual QA. Distribution-level High flexibility remains an implicit limitation, not a hidden HV parameter. | B27: Implementation order: load fixed zonal demand shares -> select scenario row -> apply FER/BESS formulas -> load the scenario-specific directional network -> map plant/cohort dispatchable assets to national controls -> run dispatch and annual QA. Distribution-level High flexibility remains an implicit limitation, not a hidden HV parameter. | C27: Implementation order: load fixed zonal demand shares -> select scenario row -> apply FER/BESS formulas -> load the scenario-specific directional network -> map plant/cohort dispatchable assets to national controls -> run dispatch and annual QA. Distribution-level High flexibility remains an implicit limitation, not a hidden HV parameter. | D27: Implementation order: load fixed zonal demand shares -> select scenario row -> apply FER/BESS formulas -> load the scenario-specific directional network -> map plant/cohort dispatchable assets to national controls -> run dispatch and annual QA. Distribution-level High flexibility remains an implicit limitation, not a hidden HV parameter. | E27: Implementation order: load fixed zonal demand shares -> select scenario row -> apply FER/BESS formulas -> load the scenario-specific directional network -> map plant/cohort dispatchable assets to national controls -> run dispatch and annual QA. Distribution-level High flexibility remains an implicit limitation, not a hidden HV parameter. | F27: Implementation order: load fixed zonal demand shares -> select scenario row -> apply FER/BESS formulas -> load the scenario-specific directional network -> map plant/cohort dispatchable assets to national controls -> run dispatch and annual QA. Distribution-level High flexibility remains an implicit limitation, not a hidden HV parameter. | G27: Implementation order: load fixed zonal demand shares -> select scenario row -> apply FER/BESS formulas -> load the scenario-specific directional network -> map plant/cohort dispatchable assets to national controls -> run dispatch and annual QA. Distribution-level High flexibility remains an implicit limitation, not a hidden HV parameter. | H27: Implementation order: load fixed zonal demand shares -> select scenario row -> apply FER/BESS formulas -> load the scenario-specific directional network -> map plant/cohort dispatchable assets to national controls -> run dispatch and annual QA. Distribution-level High flexibility remains an implicit limitation, not a hidden HV parameter. | I27: Implementation order: load fixed zonal demand shares -> select scenario row -> apply FER/BESS formulas -> load the scenario-specific directional network -> map plant/cohort dispatchable assets to national controls -> run dispatch and annual QA. Distribution-level High flexibility remains an implicit limitation, not a hidden HV parameter. | J27: Implementation order: load fixed zonal demand shares -> select scenario row -> apply FER/BESS formulas -> load the scenario-specific directional network -> map plant/cohort dispatchable assets to national controls -> run dispatch and annual QA. Distribution-level High flexibility remains an implicit limitation, not a hidden HV parameter. | K27: Implementation order: load fixed zonal demand shares -> select scenario row -> apply FER/BESS formulas -> load the scenario-specific directional network -> map plant/cohort dispatchable assets to national controls -> run dispatch and annual QA. Distribution-level High flexibility remains an implicit limitation, not a hidden HV parameter. | L27: Implementation order: load fixed zonal demand shares -> select scenario row -> apply FER/BESS formulas -> load the scenario-specific directional network -> map plant/cohort dispatchable assets to national controls -> run dispatch and annual QA. Distribution-level High flexibility remains an implicit limitation, not a hidden HV parameter.
